notebooks/Chapter_6_examples/example_5__bcd_seven_segment/bcd_seven_segment.sv
// bcd_seven_segment.sv
// BCD to Seven-Segment Display Decoder
// Converts 4-bit BCD input (0-9) to 7-segment display pattern

module bcd_seven_segment (
    input  logic [3:0] bcd_in,      // 4-bit BCD input (0-9)
    output logic [6:0] segments     // 7-segment output [a,b,c,d,e,f,g]
);

    // Seven-segment display layout:
    //  aaa
    // f   b
    // f   b
    //  ggg
    // e   c
    // e   c
    //  ddd
    
    // segments[6] = a, segments[5] = b, segments[4] = c, segments[3] = d
    // segments[2] = e, segments[1] = f, segments[0] = g
    // Active HIGH (1 = segment ON, 0 = segment OFF)

    always_comb begin
        case (bcd_in)
            4'h0: segments = 7'b1111110; // Display "0" - all except g
            4'h1: segments = 7'b0110000; // Display "1" - b,c only
            4'h2: segments = 7'b1101101; // Display "2" - a,b,d,e,g
            4'h3: segments = 7'b1111001; // Display "3" - a,b,c,d,g
            4'h4: segments = 7'b0110011; // Display "4" - b,c,f,g
            4'h5: segments = 7'b1011011; // Display "5" - a,c,d,f,g
            4'h6: segments = 7'b1011111; // Display "6" - a,c,d,e,f,g
            4'h7: segments = 7'b1110000; // Display "7" - a,b,c
            4'h8: segments = 7'b1111111; // Display "8" - all segments
            4'h9: segments = 7'b1111011; // Display "9" - a,b,c,d,f,g
            default: segments = 7'b0000000; // Blank display for invalid BCD
        endcase
    end

    // Display decoder operation for simulation
    always_comb begin
        case (bcd_in)
            4'h0: $display(
                "BCD Decoder: %h -> '0' (segments: %7b)", bcd_in, segments);
            4'h1: $display(
                "BCD Decoder: %h -> '1' (segments: %7b)", bcd_in, segments);
            4'h2: $display(
                "BCD Decoder: %h -> '2' (segments: %7b)", bcd_in, segments);
            4'h3: $display(
                "BCD Decoder: %h -> '3' (segments: %7b)", bcd_in, segments);
            4'h4: $display(
                "BCD Decoder: %h -> '4' (segments: %7b)", bcd_in, segments);
            4'h5: $display(
                "BCD Decoder: %h -> '5' (segments: %7b)", bcd_in, segments);
            4'h6: $display(
                "BCD Decoder: %h -> '6' (segments: %7b)", bcd_in, segments);
            4'h7: $display(
                "BCD Decoder: %h -> '7' (segments: %7b)", bcd_in, segments);
            4'h8: $display(
                "BCD Decoder: %h -> '8' (segments: %7b)", bcd_in, segments);
            4'h9: $display(
                "BCD Decoder: %h -> '9' (segments: %7b)", bcd_in, segments);
            default: $display(
                "BCD Decoder: %h -> BLANK (invalid BCD)", bcd_in);
        endcase
    end

endmodule

notebooks/Chapter_6_examples/example_5__bcd_seven_segment/bcd_seven_segment_testbench.sv
// bcd_seven_segment_testbench.sv
module bcd_testbench;

    // Test signals
    logic [3:0] test_bcd;
    logic [6:0] display_segments;

    // Expected patterns for verification
    logic [6:0] expected_patterns [0:9] = '{
        7'b1111110, // 0
        7'b0110000, // 1
        7'b1101101, // 2
        7'b1111001, // 3
        7'b0110011, // 4
        7'b1011011, // 5
        7'b1011111, // 6
        7'b1110000, // 7
        7'b1111111, // 8
        7'b1111011  // 9
    };

    // Instantiate the design under test
    bcd_seven_segment DUT (
        .bcd_in(test_bcd),
        .segments(display_segments)
    );

    initial begin
        // Setup waveform dumping
        $dumpfile("bcd_testbench.vcd");
        $dumpvars(0, bcd_testbench);
        
        $display("=== BCD to Seven-Segment Decoder Test ===");
        $display("Segment order: [a,b,c,d,e,f,g] (MSB to LSB)");
        $display("Display layout:");
        $display("  aaa  ");
        $display(" f   b ");
        $display(" f   b ");
        $display("  ggg  ");
        $display(" e   c ");
        $display(" e   c ");
        $display("  ddd  ");
        $display();
        
        // Test all valid BCD inputs (0-9)
        $display("Testing valid BCD inputs (0-9):");
        for (int i = 0; i <= 9; i++) begin
            test_bcd = i[3:0];
            #10;
            
            // Verify the output
            if (display_segments == expected_patterns[i]) begin
                $display("✓ BCD %0d: PASS - Segments: %7b", i, display_segments);
            end else begin
                $display("✗ BCD %0d: FAIL - Expected: %7b, Got: %7b", 
                        i, expected_patterns[i], display_segments);
            end
        end
        
        $display();
        
        // Test invalid BCD inputs (10-15)
        $display("Testing invalid BCD inputs (A-F):");
        for (int i = 10; i <= 15; i++) begin
            test_bcd = i[3:0];
            #10;
            
            if (display_segments == 7'b0000000) begin
                $display("✓ BCD %X: PASS - Blank display (segments: %7b)", i, display_segments);
            end else begin
                $display("✗ BCD %X: FAIL - Expected blank, Got: %7b", i, display_segments);
            end
        end
        
        $display();
        
        // Visual representation test
        $display("Visual representation of each digit:");
        for (int i = 0; i <= 9; i++) begin
            test_bcd = i[3:0];
            #10;
            $display("Digit %0d:", i);
            display_seven_segment(display_segments);
            $display();
        end
        
        $display("=== BCD Decoder Test Complete ===");
        $finish;
    end

    // Function to display seven-segment pattern visually
    task display_seven_segment(logic [6:0] seg);
        string a, b, c, d, e, f, g;
        
        // Convert segment bits to display characters
        a = seg[6] ? "###" : "   ";
        b = seg[5] ? "#" : " ";
        c = seg[4] ? "#" : " ";
        d = seg[3] ? "###" : "   ";
        e = seg[2] ? "#" : " ";
        f = seg[1] ? "#" : " ";
        g = seg[0] ? "###" : "   ";
        
        // Display the seven-segment pattern
        $display(" %s ", a);
        $display("%s   %s", f, b);
        $display("%s   %s", f, b);
        $display(" %s ", g);
        $display("%s   %s", e, c);
        $display("%s   %s", e, c);
        $display(" %s ", d);
    endtask

    // Monitor for any changes
    always @(display_segments) begin
        #1; // Small delay for clean display
    end

endmodule

notebooks/Chapter_6_examples/example_5__bcd_seven_segment/bcd_testbench.vcd
$version Generated by VerilatedVcd $end
$timescale 1ps $end
 $scope module $rootio $end
 $upscope $end
 $scope module bcd_testbench $end
  $var wire 4 - test_bcd [3:0] $end
  $var wire 7 . display_segments [6:0] $end
  $var wire 7 # expected_patterns[0] [6:0] $end
  $var wire 7 $ expected_patterns[1] [6:0] $end
  $var wire 7 % expected_patterns[2] [6:0] $end
  $var wire 7 & expected_patterns[3] [6:0] $end
  $var wire 7 ' expected_patterns[4] [6:0] $end
  $var wire 7 ( expected_patterns[5] [6:0] $end
  $var wire 7 ) expected_patterns[6] [6:0] $end
  $var wire 7 * expected_patterns[7] [6:0] $end
  $var wire 7 + expected_patterns[8] [6:0] $end
  $var wire 7 , expected_patterns[9] [6:0] $end
  $scope module DUT $end
   $var wire 4 - bcd_in [3:0] $end
   $var wire 7 . segments [6:0] $end
  $upscope $end
  $scope module unnamedblk1 $end
   $var wire 32 / i [31:0] $end
  $upscope $end
  $scope module unnamedblk2 $end
   $var wire 32 0 i [31:0] $end
  $upscope $end
  $scope module unnamedblk3 $end
   $var wire 32 1 i [31:0] $end
  $upscope $end
 $upscope $end
$enddefinitions $end


#0
b1111110 #
b0110000 $
b1101101 %
b1111001 &
b0110011 '
b1011011 (
b1011111 )
b1110000 *
b1111111 +
b1111011 ,
b0000 -
b1111110 .
b00000000000000000000000000000000 /
b00000000000000000000000000000000 0
b00000000000000000000000000000000 1
#10
b0001 -
b0110000 .
b00000000000000000000000000000001 /
#20
b0010 -
b1101101 .
b00000000000000000000000000000010 /
#30
b0011 -
b1111001 .
b00000000000000000000000000000011 /
#40
b0100 -
b0110011 .
b00000000000000000000000000000100 /
#50
b0101 -
b1011011 .
b00000000000000000000000000000101 /
#60
b0110 -
b1011111 .
b00000000000000000000000000000110 /
#70
b0111 -
b1110000 .
b00000000000000000000000000000111 /
#80
b1000 -
b1111111 .
b00000000000000000000000000001000 /
#90
b1001 -
b1111011 .
b00000000000000000000000000001001 /
#100
b1010 -
b0000000 .
b00000000000000000000000000001010 /
#110
b1011 -
b00000000000000000000000000001011 0
#120
b1100 -
b00000000000000000000000000001100 0
#130
b1101 -
b00000000000000000000000000001101 0
#140
b1110 -
b00000000000000000000000000001110 0
#150
b1111 -
b00000000000000000000000000001111 0
#160
b0000 -
b1111110 .
b00000000000000000000000000010000 0
#170
b0001 -
b0110000 .
b00000000000000000000000000000001 1
#180
b0010 -
b1101101 .
b00000000000000000000000000000010 1
#190
b0011 -
b1111001 .
b00000000000000000000000000000011 1
#200
b0100 -
b0110011 .
b00000000000000000000000000000100 1
#210
b0101 -
b1011011 .
b00000000000000000000000000000101 1
#220
b0110 -
b1011111 .
b00000000000000000000000000000110 1
#230
b0111 -
b1110000 .
b00000000000000000000000000000111 1
#240
b1000 -
b1111111 .
b00000000000000000000000000001000 1
#250
b1001 -
b1111011 .
b00000000000000000000000000001001 1
#260
b00000000000000000000000000001010 1
