notebooks/Chapter_4_examples/example_13__shift_register/shift_register.sv
// shift_register.sv
module shift_register (
    input  logic       clk,
    input  logic       rst_n,
    input  logic       serial_in,
    output logic [7:0] parallel_out
);

    always_ff @(posedge clk or negedge rst_n) begin
        if (!rst_n) begin
            parallel_out <= 8'h00;
            $display("Shift Register: Reset - parallel_out cleared");
        end else begin
            parallel_out <= {parallel_out[6:0], serial_in};
            $display("Shift Register: Shifted in %b, parallel_out = %b", serial_in, {parallel_out[6:0], serial_in});
        end
    end

endmodule

notebooks/Chapter_4_examples/example_13__shift_register/shift_register_testbench.sv
// shift_register_testbench.sv
module shift_register_testbench;    // Testbench module
    logic clk, rst_n, serial_in;
    logic [7:0] parallel_out;
    logic [7:0] test_pattern = 8'b10110011;
    
    shift_register SHIFT_REG_DUT (.*);  // Instantiate shift register design under test
    
    // Clock generation
    initial begin
        clk = 0;
        forever #5 clk = ~clk;
    end
    
    // Main test sequence
    initial begin
        // Dump waves
        $dumpfile("shift_register_testbench.vcd");      // Specify the VCD file
        $dumpvars(0, shift_register_testbench);         // Dump all variables in the test module
        
        $display();                                     // Display empty line
        $display("Testbench: Starting shift register validation...");
        $display();                                     // Display empty line
        
        rst_n = 0;
        serial_in = 0;
        
        #10 rst_n = 1;
        $display("Testbench: Reset released, starting shift operations...");
        
        // Shift in test pattern 10110011
        for (int i = 7; i >= 0; i--) begin
            @(posedge clk);
            serial_in = test_pattern[i];
        end
        
        @(posedge clk);
        $display();                                     // Display empty line
        $display("Testbench: Final parallel output: %b", parallel_out);
        $display("Testbench: Shift register validation completed!");
        $display();                                     // Display empty line
        $finish;
    end

endmodule

notebooks/Chapter_4_examples/example_13__shift_register/shift_register_testbench.vcd
$version Generated by VerilatedVcd $end
$timescale 1ps $end
 $scope module $rootio $end
 $upscope $end
 $scope module shift_register_testbench $end
  $var wire 1 # clk $end
  $var wire 1 $ rst_n $end
  $var wire 1 % serial_in $end
  $var wire 8 & parallel_out [7:0] $end
  $var wire 8 ( test_pattern [7:0] $end
  $scope module SHIFT_REG_DUT $end
   $var wire 1 # clk $end
   $var wire 1 $ rst_n $end
   $var wire 1 % serial_in $end
   $var wire 8 & parallel_out [7:0] $end
  $upscope $end
  $scope module unnamedblk1 $end
   $var wire 32 ' i [31:0] $end
  $upscope $end
 $upscope $end
$enddefinitions $end


#0
0#
0$
0%
b00000000 &
b00000000000000000000000000000000 '
b10110011 (
#5
1#
#10
0#
1$
#15
1#
1%
b00000001 &
b00000000000000000000000000000110 '
#20
0#
#25
1#
0%
b00000010 &
b00000000000000000000000000000101 '
#30
0#
#35
1#
1%
b00000101 &
b00000000000000000000000000000100 '
#40
0#
#45
1#
b00001011 &
b00000000000000000000000000000011 '
#50
0#
#55
1#
0%
b00010110 &
b00000000000000000000000000000010 '
#60
0#
#65
1#
b00101100 &
b00000000000000000000000000000001 '
#70
0#
#75
1#
1%
b01011001 &
b00000000000000000000000000000000 '
#80
0#
#85
1#
b10110011 &
b11111111111111111111111111111111 '
#90
0#
#95
1#
b01100111 &
