notebooks/Chapter_8_examples/example_6__sparse_memory_model/sparse_memory_controller.sv
// sparse_memory_controller.sv
module sparse_memory_controller ();

  // Sparse memory using associative array - only stores written addresses
  logic [31:0] sparse_memory_data [logic [31:0]];
  
  // Memory interface signals
  logic [31:0] memory_address;
  logic [31:0] write_data;
  logic [31:0] read_data;
  logic        write_enable;
  logic        read_enable;
  logic        data_valid;

  // Keep track of written addresses using a separate array
  logic written_addresses [logic [31:0]];

  // Memory write operation - triggered by write_enable
  always @(posedge write_enable) begin
    if (write_enable) begin
      sparse_memory_data[memory_address] = write_data;
      written_addresses[memory_address] = 1'b1;
      $display("WRITE: Address 0x%08h = 0x%08h", 
               memory_address, write_data);
    end
  end

  // Memory read operation - combinational read
  always_comb begin
    read_data = 32'hzzzz_zzzz;
    data_valid = 1'b0;
    
    if (read_enable) begin
      if (written_addresses[memory_address] == 1'b1) begin
        read_data = sparse_memory_data[memory_address];
        data_valid = 1'b1;
      end else begin
        read_data = 32'h0000_0000;  // Default value for unwritten addresses
        data_valid = 1'b0;
      end
    end
  end

  // Display memory statistics
  task automatic display_memory_statistics();
    int used_addresses;
    
    used_addresses = 0;
    
    // Count used addresses
    foreach (written_addresses[addr]) begin
      if (written_addresses[addr] == 1'b1) begin
        used_addresses++;
      end
    end
    
    $display("Memory Statistics: %0d addresses in use", used_addresses);
    
    // Show all stored addresses
    if (used_addresses > 0) begin
      $display("Stored addresses:");
      foreach (written_addresses[addr]) begin
        if (written_addresses[addr] == 1'b1) begin
          $display("  0x%08h: 0x%08h", addr, sparse_memory_data[addr]);
        end
      end
    end
  endtask

endmodule

notebooks/Chapter_8_examples/example_6__sparse_memory_model/sparse_memory_controller_testbench.sv
// sparse_memory_controller_testbench.sv
module sparse_memory_testbench;

  // Instantiate the sparse memory controller
  sparse_memory_controller memory_controller_instance();

  // Test addresses - sparse pattern to demonstrate efficiency
  logic [31:0] test_addresses [5] = '{
    32'h0000_1000,  // Low address
    32'h8000_0000,  // High address  
    32'hFFFF_F000,  // Very high address
    32'h0000_2000,  // Another low address
    32'h4000_0000   // Mid-range address
  };

  logic [31:0] test_data [5] = '{
    32'hDEAD_BEEF,
    32'hCAFE_BABE,
    32'h1234_5678,
    32'hABCD_EF00,
    32'h5555_AAAA
  };

  // Unwritten test addresses
  logic [31:0] unwritten_addresses [3] = '{
    32'h0000_0500,  // Between written addresses
    32'h9000_0000,  // High unwritten address
    32'h0000_0000   // Very low address
  };

  initial begin
    // Setup waveform dumping
    $dumpfile("sparse_memory_testbench.vcd");
    $dumpvars(0, sparse_memory_testbench);

    $display("=== Sparse Memory Model Demonstration ===");
    $display();

    // Initialize control signals
    memory_controller_instance.write_enable = 1'b0;
    memory_controller_instance.read_enable = 1'b0;
    memory_controller_instance.memory_address = 32'h0000_0000;
    memory_controller_instance.write_data = 32'h0000_0000;

    #10;

    // Phase 1: Write data to sparse addresses
    $display("Phase 1: Writing to sparse memory addresses");
    for (int i = 0; i < 5; i++) begin
      #10;
      memory_controller_instance.memory_address = test_addresses[i];
      memory_controller_instance.write_data = test_data[i];
      memory_controller_instance.read_enable = 1'b0;
      #1;
      memory_controller_instance.write_enable = 1'b1;
      #1;
      memory_controller_instance.write_enable = 1'b0;
      #1;
    end

    #10;
    $display();
    memory_controller_instance.display_memory_statistics();
    $display();

    // Phase 2: Read from written addresses
    $display("Phase 2: Reading from written addresses");
    for (int i = 0; i < 5; i++) begin
      #10;
      memory_controller_instance.memory_address = test_addresses[i];
      memory_controller_instance.write_enable = 1'b0;
      memory_controller_instance.read_enable = 1'b1;
      #1;
      $display("READ:  Address 0x%08h = 0x%08h (VALID)", 
               test_addresses[i], memory_controller_instance.read_data);
      memory_controller_instance.read_enable = 1'b0;
      #1;
    end

    #10;
    $display();

    // Phase 3: Read from unwritten addresses
    $display("Phase 3: Reading from uninitialized addresses");

    for (int i = 0; i < 3; i++) begin
      #10;
      memory_controller_instance.memory_address = unwritten_addresses[i];
      memory_controller_instance.write_enable = 1'b0;
      memory_controller_instance.read_enable = 1'b1;
      #1;
      $display("READ:  Address 0x%08h = 0x%08h (UNINITIALIZED)", 
               unwritten_addresses[i], memory_controller_instance.read_data);
      memory_controller_instance.read_enable = 1'b0;
      #1;
    end

    #10;
    $display();
    $display("=== Test Complete ===");
    $display("Sparse memory model efficiently stores only 5 addresses");
    $display();

    #50;
    $finish;
  end

endmodule

notebooks/Chapter_8_examples/example_6__sparse_memory_model/sparse_memory_testbench.vcd
$version Generated by VerilatedVcd $end
$timescale 1ps $end
 $scope module $rootio $end
 $upscope $end
 $scope module sparse_memory_testbench $end
  $var wire 32 # test_addresses[0] [31:0] $end
  $var wire 32 $ test_addresses[1] [31:0] $end
  $var wire 32 % test_addresses[2] [31:0] $end
  $var wire 32 & test_addresses[3] [31:0] $end
  $var wire 32 ' test_addresses[4] [31:0] $end
  $var wire 32 ( test_data[0] [31:0] $end
  $var wire 32 ) test_data[1] [31:0] $end
  $var wire 32 * test_data[2] [31:0] $end
  $var wire 32 + test_data[3] [31:0] $end
  $var wire 32 , test_data[4] [31:0] $end
  $var wire 32 - unwritten_addresses[0] [31:0] $end
  $var wire 32 . unwritten_addresses[1] [31:0] $end
  $var wire 32 / unwritten_addresses[2] [31:0] $end
  $scope module memory_controller_instance $end
   $var wire 32 0 memory_address [31:0] $end
   $var wire 32 1 write_data [31:0] $end
   $var wire 32 7 read_data [31:0] $end
   $var wire 1 2 write_enable $end
   $var wire 1 3 read_enable $end
   $var wire 1 8 data_valid $end
  $upscope $end
  $scope module unnamedblk1 $end
   $var wire 32 4 i [31:0] $end
  $upscope $end
  $scope module unnamedblk2 $end
   $var wire 32 5 i [31:0] $end
  $upscope $end
  $scope module unnamedblk3 $end
   $var wire 32 6 i [31:0] $end
  $upscope $end
 $upscope $end
$enddefinitions $end


#0
b00000000000000000001000000000000 #
b10000000000000000000000000000000 $
b11111111111111111111000000000000 %
b00000000000000000010000000000000 &
b01000000000000000000000000000000 '
b11011110101011011011111011101111 (
b11001010111111101011101010111110 )
b00010010001101000101011001111000 *
b10101011110011011110111100000000 +
b01010101010101011010101010101010 ,
b00000000000000000000010100000000 -
b10010000000000000000000000000000 .
b00000000000000000000000000000000 /
b00000000000000000000000000000000 0
b00000000000000000000000000000000 1
02
03
b00000000000000000000000000000000 4
b00000000000000000000000000000000 5
b00000000000000000000000000000000 6
b00000000000000000000000000000000 7
08
#20
b00000000000000000001000000000000 0
b11011110101011011011111011101111 1
#21
12
#22
02
#23
b00000000000000000000000000000001 4
#33
b10000000000000000000000000000000 0
b11001010111111101011101010111110 1
#34
12
#35
02
#36
b00000000000000000000000000000010 4
#46
b11111111111111111111000000000000 0
b00010010001101000101011001111000 1
#47
12
#48
02
#49
b00000000000000000000000000000011 4
#59
b00000000000000000010000000000000 0
b10101011110011011110111100000000 1
#60
12
#61
02
#62
b00000000000000000000000000000100 4
#72
b01000000000000000000000000000000 0
b01010101010101011010101010101010 1
#73
12
#74
02
#75
b00000000000000000000000000000101 4
#95
b00000000000000000001000000000000 0
13
b11011110101011011011111011101111 7
18
#96
03
08
#97
b00000000000000000000000000000001 5
#107
b10000000000000000000000000000000 0
13
b11001010111111101011101010111110 7
18
#108
03
08
#109
b00000000000000000000000000000010 5
#119
b11111111111111111111000000000000 0
13
b00010010001101000101011001111000 7
18
#120
03
08
#121
b00000000000000000000000000000011 5
#131
b00000000000000000010000000000000 0
13
b10101011110011011110111100000000 7
18
#132
03
08
#133
b00000000000000000000000000000100 5
#143
b01000000000000000000000000000000 0
13
b01010101010101011010101010101010 7
18
#144
03
08
#145
b00000000000000000000000000000101 5
#165
b00000000000000000000010100000000 0
13
#166
03
#167
b00000000000000000000000000000001 6
#177
b10010000000000000000000000000000 0
13
#178
03
#179
b00000000000000000000000000000010 6
#189
b00000000000000000000000000000000 0
13
#190
03
#191
b00000000000000000000000000000011 6
