notebooks/Chapter_6_examples/example_16__data_bus_latch/data_bus_latch.sv
// data_bus_latch.sv - Fixed version without circular logic
module data_bus_latch (
    input  logic        clk,
    input  logic        rst_n,
    
    // Control signals
    input  logic        latch_enable,      // Enable latch operation
    input  logic        cpu_to_bus_dir,    // Direction: 1=CPU->Bus, 0=Bus->CPU
    input  logic        bus_output_enable, // Enable bus output drivers
    
    // CPU side interface
    inout  logic [7:0]  cpu_data,          // Bidirectional CPU data bus
    
    // External bus interface  
    inout  logic [7:0]  ext_bus_data,      // Bidirectional external data bus
    
    // Status outputs
    output logic        latch_active,      // Latch is currently active
    output logic        bus_isolated       // Bus is isolated (high-Z)
);

    // Internal latched data storage
    logic [7:0] cpu_to_bus_latch;    // Latch for CPU->Bus direction
    logic [7:0] bus_to_cpu_latch;    // Latch for Bus->CPU direction
    
    // Previous latch enable states for edge detection
    logic prev_latch_enable;
    logic prev_cpu_to_bus_dir;
    
    // Control signals for driving the buses
    logic drive_cpu_bus;
    logic drive_ext_bus;
    
    // Update previous states on clock edge
    always_ff @(posedge clk or negedge rst_n) begin
        if (!rst_n) begin
            prev_latch_enable <= 1'b0;
            prev_cpu_to_bus_dir <= 1'b0;
        end else begin
            prev_latch_enable <= latch_enable;
            prev_cpu_to_bus_dir <= cpu_to_bus_dir;
        end
    end
    
    // Latch data on the rising edge of latch_enable
    always_ff @(posedge clk or negedge rst_n) begin
        if (!rst_n) begin
            cpu_to_bus_latch <= 8'h00;
            bus_to_cpu_latch <= 8'h00;
        end else begin
            // Latch on rising edge of latch_enable
            if (latch_enable && !prev_latch_enable) begin
                if (cpu_to_bus_dir) begin
                    // CPU->Bus: latch CPU data
                    cpu_to_bus_latch <= cpu_data;
                    $display(
                        "Time %0t: Data Bus Latch - CPU->Bus direction, latching CPU data: 0x%02h", 
                        $time, cpu_data);
                end else begin
                    // Bus->CPU: latch external bus data
                    bus_to_cpu_latch <= ext_bus_data;
                    $display(
                        "Time %0t: Data Bus Latch - Bus->CPU direction, latching Bus data: 0x%02h", 
                        $time, ext_bus_data);
                end
            end
        end
    end
    
    // Drive control logic - only drive when latch is active and output is enabled
    assign drive_ext_bus = latch_enable && cpu_to_bus_dir && bus_output_enable;
    assign drive_cpu_bus = latch_enable && !cpu_to_bus_dir && bus_output_enable;
    
    // Bidirectional bus control
    assign cpu_data = drive_cpu_bus ? bus_to_cpu_latch : 8'bz;
    assign ext_bus_data = drive_ext_bus ? cpu_to_bus_latch : 8'bz;
    
    // Status signals
    assign latch_active = latch_enable;
    assign bus_isolated = !bus_output_enable;
    
    // Debug output for bus driving
    always @(posedge bus_output_enable) begin
        if (latch_enable) begin
            if (cpu_to_bus_dir) begin
                $display(
                    "Time %0t: Data Bus Latch - Driving ext_bus with latched data: 0x%02h", 
                    $time, cpu_to_bus_latch);
            end else begin
                $display(
                    "Time %0t: Data Bus Latch - Driving cpu_data with latched data: 0x%02h", 
                    $time, bus_to_cpu_latch);
            end
        end
    end
    
    always @(negedge bus_output_enable) begin
        $display(
            "Time %0t: Data Bus Latch - Output disabled, buses isolated",
            $time);
    end
    
    initial $display(
        "Data Bus Latch initialized - Bidirectional data isolation and timing control");

endmodule

notebooks/Chapter_6_examples/example_16__data_bus_latch/data_bus_latch_testbench.sv
// data_bus_latch_testbench.sv
module data_bus_latch_testbench;

    // Clock and reset
    logic clk;
    logic rst_n;
    
    // Control signals
    logic latch_enable;
    logic cpu_to_bus_dir;
    logic bus_output_enable;
    
    // Data buses
    wire [7:0] cpu_data;
    wire [7:0] ext_bus_data;
    
    // Status signals
    logic latch_active;
    logic bus_isolated;
    
    // Test drivers
    logic [7:0] cpu_data_driver;
    logic [7:0] ext_bus_data_driver;
    logic       cpu_drive_enable;
    logic       ext_bus_drive_enable;
    
    // Drive the bidirectional buses
    assign cpu_data = cpu_drive_enable ? cpu_data_driver : 8'bz;
    assign ext_bus_data = ext_bus_drive_enable ? ext_bus_data_driver : 8'bz;
    
    // Instantiate the data bus latch
    data_bus_latch DATA_BUS_LATCH_INST (
        .clk(clk),
        .rst_n(rst_n),
        .latch_enable(latch_enable),
        .cpu_to_bus_dir(cpu_to_bus_dir),
        .bus_output_enable(bus_output_enable),
        .cpu_data(cpu_data),
        .ext_bus_data(ext_bus_data),
        .latch_active(latch_active),
        .bus_isolated(bus_isolated)
    );
    
    // Clock generation
    initial begin
        clk = 0;
        forever #5 clk = ~clk;  // 10ns clock period
    end
    
    // Helper task to display bus states
    task display_bus_state(string test_name);
        $display("%s - CPU: 0x%02h, ExtBus: 0x%02h, LatchActive: %b, Isolated: %b", 
                 test_name, cpu_data, ext_bus_data, latch_active, bus_isolated);
    endtask
    
    // Test sequence
    initial begin
        // Initialize signals
        rst_n = 0;
        latch_enable = 0;
        cpu_to_bus_dir = 0;
        bus_output_enable = 0;
        cpu_data_driver = 8'h00;
        ext_bus_data_driver = 8'h00;
        cpu_drive_enable = 0;
        ext_bus_drive_enable = 0;
        
        // Dump waves
        $dumpfile("data_bus_latch_testbench.vcd");
        $dumpvars(0, data_bus_latch_testbench);
        
        $display();
        $display("=== Data Bus Latch Test ===");
        $display();
        
        // Release reset
        #20 rst_n = 1;
        #10;
        
        // Test 1: CPU to Bus transfer
        $display("Test 1: CPU to Bus data transfer");
        cpu_data_driver = 8'hAA;
        cpu_drive_enable = 1;
        cpu_to_bus_dir = 1;  // CPU->Bus direction
        #10;
        display_bus_state("  Initial state");
        
        // Enable latch (should latch CPU data)
        latch_enable = 1;
        #10;
        display_bus_state("  Latch enabled");
        
        // Change CPU data (should not affect latched value)
        cpu_data_driver = 8'hFF;
        #10;
        display_bus_state("  CPU data changed");
        
        // Enable bus output (should drive external bus)
        bus_output_enable = 1;
        #10;
        display_bus_state("  Bus output enabled");
        
        // Disable CPU driver to see latch driving bus
        cpu_drive_enable = 0;
        #10;
        display_bus_state("  CPU driver disabled");
        
        // Cleanup
        bus_output_enable = 0;
        latch_enable = 0;
        #20;
        
        // Test 2: Bus to CPU transfer
        $display("Test 2: Bus to CPU data transfer");
        ext_bus_data_driver = 8'h55;
        ext_bus_drive_enable = 1;
        cpu_to_bus_dir = 0;  // Bus->CPU direction
        #10;
        display_bus_state("  Initial state");
        
        // Enable latch (should latch bus data)
        latch_enable = 1;
        #10;
        display_bus_state("  Latch enabled");
        
        // Change bus data (should not affect latched value)
        ext_bus_data_driver = 8'h33;
        #10;
        display_bus_state("  Bus data changed");
        
        // Enable bus output (should drive CPU bus)
        bus_output_enable = 1;
        #10;
        display_bus_state("  Bus output enabled");
        
        // Disable external bus driver to see latch driving CPU
        ext_bus_drive_enable = 0;
        #10;
        display_bus_state("  Ext bus driver disabled");
        
        // Cleanup
        bus_output_enable = 0;
        latch_enable = 0;
        #20;
        
        // Test 3: Bus isolation
        $display("Test 3: Bus isolation test");
        cpu_data_driver = 8'hCC;
        ext_bus_data_driver = 8'h99;
        cpu_drive_enable = 1;
        ext_bus_drive_enable = 1;
        #10;
        display_bus_state("  Both buses driven");
        
        // Enable latch but keep output disabled (isolation)
        latch_enable = 1;
        cpu_to_bus_dir = 1;
        #10;
        display_bus_state("  Latch enabled, output disabled");
        
        // Disable external drivers
        cpu_drive_enable = 0;
        ext_bus_drive_enable = 0;
        #10;
        display_bus_state("  All drivers disabled (isolated)");
        
        // Enable output
        bus_output_enable = 1;
        #10;
        display_bus_state("  Output enabled");
        
        // Cleanup
        bus_output_enable = 0;
        latch_enable = 0;
        #20;
        
        // Test 4: Multiple transfers with different data
        $display("Test 4: Multiple transfers");
        for (int i = 0; i < 4; i++) begin
            logic [7:0] test_data = 8'h10 + 8'(i * 8'h11);
            
            $display("  Transfer %0d: Data 0x%02h", i+1, test_data);
            
            // Setup data
            if (i % 2 == 0) begin
                // CPU to Bus
                cpu_data_driver = test_data;
                cpu_drive_enable = 1;
                ext_bus_drive_enable = 0;
                cpu_to_bus_dir = 1;
            end else begin
                // Bus to CPU
                ext_bus_data_driver = test_data;
                ext_bus_drive_enable = 1;
                cpu_drive_enable = 0;
                cpu_to_bus_dir = 0;
            end
            
            #10;
            
            // Latch and transfer
            latch_enable = 1;
            #10;
            bus_output_enable = 1;
            #10;
            display_bus_state("    Transfer complete");
            
            // Cleanup
            bus_output_enable = 0;
            latch_enable = 0;
            cpu_drive_enable = 0;
            ext_bus_drive_enable = 0;
            #10;
        end
        
        // Test 5: Timing control demonstration
        $display("Test 5: Timing control demonstration");
        cpu_data_driver = 8'hDE;
        cpu_drive_enable = 1;
        cpu_to_bus_dir = 1;
        
        $display("  Phase 1: Setup data");
        #10;
        display_bus_state("    Data setup");
        
        $display("  Phase 2: Latch data");
        latch_enable = 1;
        #10;
        display_bus_state("    Data latched");
        
        $display("  Phase 3: Remove source data");
        cpu_drive_enable = 0;
        #10;
        display_bus_state("    Source removed");
        
        $display("  Phase 4: Drive output");
        bus_output_enable = 1;
        #10;
        display_bus_state("    Output driving");
        
        $display("  Phase 5: Complete transfer");
        bus_output_enable = 0;
        latch_enable = 0;
        #10;
        display_bus_state("    Transfer complete");
        
        $display();
        $display("=== All tests completed ===");
        $display();
        
        #50 $finish;
    end

endmodule

notebooks/Chapter_6_examples/example_16__data_bus_latch/data_bus_latch_testbench.vcd
$version Generated by VerilatedVcd $end
$timescale 1ps $end
 $scope module $rootio $end
 $upscope $end
 $scope module data_bus_latch_testbench $end
  $var wire 1 2 clk $end
  $var wire 1 # rst_n $end
  $var wire 1 $ latch_enable $end
  $var wire 1 % cpu_to_bus_dir $end
  $var wire 1 & bus_output_enable $end
  $var wire 8 3 cpu_data [7:0] $end
  $var wire 8 4 ext_bus_data [7:0] $end
  $var wire 1 $ latch_active $end
  $var wire 1 ' bus_isolated $end
  $var wire 8 ( cpu_data_driver [7:0] $end
  $var wire 8 ) ext_bus_data_driver [7:0] $end
  $var wire 1 * cpu_drive_enable $end
  $var wire 1 + ext_bus_drive_enable $end
  $scope module DATA_BUS_LATCH_INST $end
   $var wire 1 2 clk $end
   $var wire 1 # rst_n $end
   $var wire 1 $ latch_enable $end
   $var wire 1 % cpu_to_bus_dir $end
   $var wire 1 & bus_output_enable $end
   $var wire 8 3 cpu_data [7:0] $end
   $var wire 8 4 ext_bus_data [7:0] $end
   $var wire 1 $ latch_active $end
   $var wire 1 ' bus_isolated $end
   $var wire 8 . cpu_to_bus_latch [7:0] $end
   $var wire 8 / bus_to_cpu_latch [7:0] $end
   $var wire 1 0 prev_latch_enable $end
   $var wire 1 1 prev_cpu_to_bus_dir $end
   $var wire 1 5 drive_cpu_bus $end
   $var wire 1 6 drive_ext_bus $end
  $upscope $end
  $scope module unnamedblk1 $end
   $var wire 32 , i [31:0] $end
   $scope module unnamedblk2 $end
    $var wire 8 - test_data [7:0] $end
   $upscope $end
  $upscope $end
 $upscope $end
$enddefinitions $end


#0
0#
0$
0%
0&
1'
b00000000 (
b00000000 )
0*
0+
b00000000000000000000000000000000 ,
b00000000 -
b00000000 .
b00000000 /
00
01
02
b00000000 3
b00000000 4
05
06
#5
12
#10
02
#15
12
#20
1#
02
#25
12
#30
1%
b10101010 (
1*
02
b10101010 3
#35
11
12
#40
1$
02
#45
b10101010 .
10
12
#50
b11111111 (
02
b11111111 3
#55
12
#60
1&
0'
02
b10101010 4
16
#65
12
#70
0*
02
b00000000 3
#75
12
#80
0$
0&
1'
02
b00000000 4
06
#85
00
12
#90
02
#95
12
#100
0%
b01010101 )
1+
02
b01010101 4
#105
01
12
#110
1$
02
#115
b01010101 /
10
12
#120
b00110011 )
02
b00110011 4
#125
12
#130
1&
0'
02
b01010101 3
15
#135
12
#140
0+
02
b00000000 4
#145
12
#150
0$
0&
1'
02
b00000000 3
05
#155
00
12
#160
02
#165
12
#170
b11001100 (
b10011001 )
1*
1+
02
b11001100 3
b10011001 4
#175
12
#180
1$
1%
02
#185
b11001100 .
10
11
12
#190
0*
0+
02
b00000000 3
b00000000 4
#195
12
#200
1&
0'
02
b11001100 4
16
#205
12
#210
0$
0&
1'
02
b00000000 4
06
#215
00
12
#220
02
#225
12
#230
b00010000 (
1*
b00010000 -
02
b00010000 3
#235
12
#240
1$
02
#245
b00010000 .
10
12
#250
1&
0'
02
b00010000 4
16
#255
12
#260
0$
0&
1'
0*
02
b00000000 3
b00000000 4
06
#265
00
12
#270
0%
b00100001 )
1+
b00000000000000000000000000000001 ,
b00100001 -
02
b00100001 4
#275
01
12
#280
1$
02
#285
b00100001 /
10
12
#290
1&
0'
02
b00100001 3
15
#295
12
#300
0$
0&
1'
0+
02
b00000000 3
b00000000 4
05
#305
00
12
#310
1%
b00110010 (
1*
b00000000000000000000000000000010 ,
b00110010 -
02
b00110010 3
#315
11
12
#320
1$
02
#325
b00110010 .
10
12
#330
1&
0'
02
b00110010 4
16
#335
12
#340
0$
0&
1'
0*
02
b00000000 3
b00000000 4
06
#345
00
12
#350
0%
b01000011 )
1+
b00000000000000000000000000000011 ,
b01000011 -
02
b01000011 4
#355
01
12
#360
1$
02
#365
b01000011 /
10
12
#370
1&
0'
02
b01000011 3
15
#375
12
#380
0$
0&
1'
0+
02
b00000000 3
b00000000 4
05
#385
00
12
#390
1%
b11011110 (
1*
b00000000000000000000000000000100 ,
02
b11011110 3
#395
11
12
#400
1$
02
#405
b11011110 .
10
12
#410
0*
02
b00000000 3
#415
12
#420
1&
0'
02
b11011110 4
16
#425
12
#430
0$
0&
1'
02
b00000000 4
06
#435
00
12
