notebooks/Chapter_4_examples/fsm_example/fsm.sv
// fsm.sv
typedef enum logic [1:0] {
    IDLE = 2'b00,
    READ = 2'b01,
    WRITE = 2'b10,
    DONE = 2'b11
} state_t;

module fsm(
    input logic clk, rst_n, start, rw,
    output logic busy, done
);
    state_t current_state, next_state;
    
    always_ff @(posedge clk or negedge rst_n) begin
        if (!rst_n)
            current_state <= IDLE;
        else
            current_state <= next_state;
    end
    
    always_comb begin
        unique case (current_state)
            IDLE: begin
                if (start)
                    next_state = rw ? WRITE : READ;
                else
                    next_state = IDLE;
            end
            READ: next_state = DONE;
            WRITE: next_state = DONE;
            DONE: next_state = IDLE;
        endcase
    end
    
    assign busy = (current_state != IDLE);
    assign done = (current_state == DONE);
endmodule

notebooks/Chapter_4_examples/example_5__fsm/fsm_testbench.sv
// fsm_testbench.sv
module fsm_testbench;
    // Testbench signals
    logic clk, rst_n, start, rw;
    logic busy, done;
    
    // Clock generation
    initial begin
        clk = 0;
        forever #5 clk = ~clk;  // 10ns period clock
    end
    
    // Instantiate the design under test
    fsm DUT (
        .clk(clk),
        .rst_n(rst_n),
        .start(start),
        .rw(rw),
        .busy(busy),
        .done(done)
    );
    
    // Test stimulus
    initial begin
        // Dump waves
        $dumpfile("fsm_testbench.vcd");
        $dumpvars(0, fsm_testbench);
        
        $display();
        $display("Starting FSM Test");
        $display("=================");
        $display("Time\tState\t\tInputs\t\tOutputs");
        $display("    \t     \t\trst_n start rw\tbusy done");
        $display("-----------------------------------------------");
        
        // Initialize signals
        rst_n = 0;
        start = 0;
        rw = 0;
        
        // Reset test
        #10;
        $display("%4t\t%s\t%b     %b     %b\t%b    %b", 
                 $time, DUT.current_state.name(), rst_n, start, rw, busy, done);
        
        // Release reset
        rst_n = 1;
        #10;
        $display("%4t\t%s\t%b     %b     %b\t%b    %b", 
                 $time, DUT.current_state.name(), rst_n, start, rw, busy, done);
        
        // Test READ operation
        $display("\n--- Testing READ Operation ---");
        start = 1;
        rw = 0;  // READ
        #10;
        $display("%4t\t%s\t%b     %b     %b\t%b    %b", 
                 $time, DUT.current_state.name(), rst_n, start, rw, busy, done);
        
        start = 0;
        #10;
        $display("%4t\t%s\t%b     %b     %b\t%b    %b", 
                 $time, DUT.current_state.name(), rst_n, start, rw, busy, done);
        
        #10;
        $display("%4t\t%s\t%b     %b     %b\t%b    %b", 
                 $time, DUT.current_state.name(), rst_n, start, rw, busy, done);
        
        #10;
        $display("%4t\t%s\t%b     %b     %b\t%b    %b", 
                 $time, DUT.current_state.name(), rst_n, start, rw, busy, done);
        
        // Test WRITE operation
        $display("\n--- Testing WRITE Operation ---");
        start = 1;
        rw = 1;  // WRITE
        #10;
        $display("%4t\t%s\t%b     %b     %b\t%b    %b", 
                 $time, DUT.current_state.name(), rst_n, start, rw, busy, done);
        
        start = 0;
        #10;
        $display("%4t\t%s\t%b     %b     %b\t%b    %b", 
                 $time, DUT.current_state.name(), rst_n, start, rw, busy, done);
        
        #10;
        $display("%4t\t%s\t%b     %b     %b\t%b    %b", 
                 $time, DUT.current_state.name(), rst_n, start, rw, busy, done);
        
        #10;
        $display("%4t\t%s\t%b     %b     %b\t%b    %b", 
                 $time, DUT.current_state.name(), rst_n, start, rw, busy, done);
        
        // Test staying in IDLE when start is not asserted
        $display("\n--- Testing IDLE Hold ---");
        start = 0;
        rw = 0;
        #20;
        $display("%4t\t%s\t%b     %b     %b\t%b    %b", 
                 $time, DUT.current_state.name(), rst_n, start, rw, busy, done);
        
        // Test reset during operation
        $display("\n--- Testing Reset During Operation ---");
        start = 1;
        rw = 1;
        #10;
        $display("%4t\t%s\t%b     %b     %b\t%b    %b", 
                 $time, DUT.current_state.name(), rst_n, start, rw, busy, done);
        
        // Assert reset
        rst_n = 0;
        #10;
        $display("%4t\t%s\t%b     %b     %b\t%b    %b", 
                 $time, DUT.current_state.name(), rst_n, start, rw, busy, done);
        
        // Release reset
        rst_n = 1;
        start = 0;
        #10;
        $display("%4t\t%s\t%b     %b     %b\t%b    %b", 
                 $time, DUT.current_state.name(), rst_n, start, rw, busy, done);
        
        $display("\n=================");
        $display("Test completed!");
        $display();
        
        #20;
        $finish;
    end

endmodule

notebooks/Chapter_4_examples/example_5__fsm/fsm_testbench.vcd
$version Generated by VerilatedVcd $end
$timescale 1ps $end
 $scope module $rootio $end
 $upscope $end
 $scope module fsm_testbench $end
  $var wire 1 & clk $end
  $var wire 1 ' rst_n $end
  $var wire 1 ( start $end
  $var wire 1 ) rw $end
  $var wire 1 # busy $end
  $var wire 1 $ done $end
  $scope module DUT $end
   $var wire 1 & clk $end
   $var wire 1 ' rst_n $end
   $var wire 1 ( start $end
   $var wire 1 ) rw $end
   $var wire 1 # busy $end
   $var wire 1 $ done $end
   $var wire 2 % current_state [1:0] $end
   $var wire 2 * next_state [1:0] $end
  $upscope $end
 $upscope $end
$enddefinitions $end


#0
0#
0$
b00 %
0&
0'
0(
0)
b00 *
#5
1&
#10
0&
1'
#15
1&
#20
0&
1(
b01 *
#25
1#
b01 %
1&
b11 *
#30
0&
0(
#35
1$
b11 %
1&
b00 *
#40
0&
#45
0#
0$
b00 %
1&
#50
0&
#55
1&
#60
0&
1(
1)
b10 *
#65
1#
b10 %
1&
b11 *
#70
0&
0(
#75
1$
b11 %
1&
b00 *
#80
0&
#85
0#
0$
b00 %
1&
#90
0&
#95
1&
#100
0&
0)
#105
1&
#110
0&
#115
1&
#120
0&
1(
1)
b10 *
#125
1#
b10 %
1&
b11 *
#130
0#
b00 %
0&
0'
b10 *
#135
1&
#140
0&
1'
0(
b00 *
