notebooks/Chapter_6_examples/example_19__shift_register_comparison/shift_register_comparison.sv
// shift_register_comparison.sv
// Demonstrates critical differences between blocking and non-blocking assignments
// in shift register implementations - side-by-side comparison

module shift_register_comparison (
    input  logic       clk,
    input  logic       reset_n,
    input  logic       shift_enable,
    input  logic       serial_in,
    output logic [7:0] parallel_out_correct,
    output logic [7:0] parallel_out_incorrect,
    output logic       serial_out_correct,
    output logic       serial_out_incorrect
);

    // ========================================
    // CORRECT SHIFT REGISTER IMPLEMENTATION
    // Using non-blocking assignments (<=)
    // ========================================
    
    logic [7:0] shift_reg_correct;
    
    // CORRECT: Non-blocking assignments create proper shift register
    always_ff @(posedge clk or negedge reset_n) begin
        if (~reset_n) begin
            shift_reg_correct <= 8'b0;
        end else if (shift_enable) begin
            // All assignments happen simultaneously at clock edge
            shift_reg_correct[7] <= serial_in;           // New bit in
            shift_reg_correct[6] <= shift_reg_correct[7]; // Bit 7 -> 6
            shift_reg_correct[5] <= shift_reg_correct[6]; // Bit 6 -> 5
            shift_reg_correct[4] <= shift_reg_correct[5]; // Bit 5 -> 4
            shift_reg_correct[3] <= shift_reg_correct[4]; // Bit 4 -> 3
            shift_reg_correct[2] <= shift_reg_correct[3]; // Bit 3 -> 2
            shift_reg_correct[1] <= shift_reg_correct[2]; // Bit 2 -> 1
            shift_reg_correct[0] <= shift_reg_correct[1]; // Bit 1 -> 0
        end
    end
    
    // Outputs for correct implementation
    assign parallel_out_correct = shift_reg_correct;
    assign serial_out_correct = shift_reg_correct[0];

    // ========================================
    // INCORRECT SHIFT REGISTER IMPLEMENTATION  
    // Using blocking assignments (=)
    // ========================================
    
    logic [7:0] shift_reg_incorrect;
    
    // INCORRECT: Blocking assignments create wrong behavior
    always_ff @(posedge clk or negedge reset_n) begin
        if (~reset_n) begin
            shift_reg_incorrect = 8'b0;
        end else if (shift_enable) begin
            // PROBLEM: Assignments execute sequentially!
            // This creates a "shift-through" effect in one clock cycle
            shift_reg_incorrect[7] = serial_in;              // Executes first
            shift_reg_incorrect[6] = shift_reg_incorrect[7]; // Uses NEW value of [7]!
            shift_reg_incorrect[5] = shift_reg_incorrect[6]; // Uses NEW value of [6]!
            shift_reg_incorrect[4] = shift_reg_incorrect[5]; // Uses NEW value of [5]!
            shift_reg_incorrect[3] = shift_reg_incorrect[4]; // Uses NEW value of [4]!
            shift_reg_incorrect[2] = shift_reg_incorrect[3]; // Uses NEW value of [3]!
            shift_reg_incorrect[1] = shift_reg_incorrect[2]; // Uses NEW value of [2]!
            shift_reg_incorrect[0] = shift_reg_incorrect[1]; // Uses NEW value of [1]!
            // Result: serial_in propagates through ALL bits in ONE clock cycle!
        end
    end
    
    // Outputs for incorrect implementation
    assign parallel_out_incorrect = shift_reg_incorrect;
    assign serial_out_incorrect = shift_reg_incorrect[0];
    
    // Alternative correct implementation using concatenation (for reference)
    logic [7:0] shift_reg_concat;
    always_ff @(posedge clk or negedge reset_n) begin
        if (~reset_n) begin
            shift_reg_concat <= 8'b0;
        end else if (shift_enable) begin
            // This is also correct - concatenation with non-blocking assignment
            shift_reg_concat <= {serial_in, shift_reg_concat[7:1]};
        end
    end
    
    // Display educational information
    initial begin
        $display("=== SHIFT REGISTER ASSIGNMENT COMPARISON ===");
        $display("CORRECT (<=):   Each bit shifts one position per clock");
        $display("INCORRECT (=):  Input propagates through ALL bits in one clock");
        $display("=> Watch how serial_in='1' behaves differently:");
        $display("   - Correct: Takes 8 clocks to reach serial_out");
        $display("   - Incorrect: Reaches serial_out in 1 clock!");
        $display("===========================================");
    end

endmodule

notebooks/Chapter_6_examples/example_19__shift_register_comparison/shift_register_comparison_testbench.sv
// shift_register_comparison_testbench.sv
module shift_register_testbench;

    // Testbench signals
    logic       clk;
    logic       reset_n;
    logic       shift_enable;
    logic       serial_in;
    logic [7:0] parallel_out_correct;
    logic [7:0] parallel_out_incorrect;
    logic       serial_out_correct;
    logic       serial_out_incorrect;
    
    // Test pattern for serial input
    logic test_pattern [0:15] = '{1,0,1,1,0,0,1,0,1,1,1,0,0,1,1,0};
    int pattern_index = 0;
    int cycle_count = 0;
    
    // Instantiate the shift register comparison
    shift_register_comparison SHIFT_REG_INSTANCE (
        .clk(clk),
        .reset_n(reset_n),
        .shift_enable(shift_enable),
        .serial_in(serial_in),
        .parallel_out_correct(parallel_out_correct),
        .parallel_out_incorrect(parallel_out_incorrect),
        .serial_out_correct(serial_out_correct),
        .serial_out_incorrect(serial_out_incorrect)
    );
    
    // Clock generation - 10ns period
    initial begin
        clk = 0;
        forever #5 clk = ~clk;
    end
    
    // Test sequence
    initial begin
        // Dump waves for detailed analysis
        $dumpfile("shift_register_testbench.vcd");
        $dumpvars(0, shift_register_testbench);
        
        // Initialize signals
        reset_n = 0;
        shift_enable = 0;
        serial_in = 0;
        
        $display("\n=== Shift Register Assignment Comparison ===");
        $display("8-bit shift register: MSB <- serial_in ... LSB -> serial_out");
        
        // Reset sequence
        repeat(2) @(posedge clk);
        reset_n = 1;
        shift_enable = 1;
        
        $display("\n--- Test 1: Single '1' bit propagation ---");
        
        // Test 1: Send single '1' bit and observe propagation
        @(posedge clk);
        serial_in = 1;
        cycle_count++;
        $display("Cycle %0d: Input='1' -> Correct=%8b (%0d), Incorrect=%8b (%0d)", 
                 cycle_count, parallel_out_correct, parallel_out_correct, 
                 parallel_out_incorrect, parallel_out_incorrect);
        
        // Follow with zeros to see the '1' propagate
        for (int i = 0; i < 10; i++) begin
            @(posedge clk);
            serial_in = 0;
            cycle_count++;
            $display("Cycle %0d: Input='0' -> Correct=%8b (%0d), Incorrect=%8b (%0d)", 
                     cycle_count, parallel_out_correct, parallel_out_correct, 
                     parallel_out_incorrect, parallel_out_incorrect);
        end
        
        $display("\n--- Test 2: Pattern shifting ---");
        
        // Reset for pattern test
        @(posedge clk);
        reset_n = 0;
        @(posedge clk);
        reset_n = 1;
        cycle_count = 0;
        
        // Shift in test pattern
        for (int i = 0; i < 16; i++) begin
            @(posedge clk);
            serial_in = test_pattern[i];
            cycle_count++;
            
            $display("Cycle %0d: Input='%0d' -> Correct=%8b, Incorrect=%8b", 
                     cycle_count, serial_in, parallel_out_correct, parallel_out_incorrect);
            $display("         Serial Out: Correct='%0d', Incorrect='%0d'", 
                     serial_out_correct, serial_out_incorrect);
        end
        
        $display("\n--- Test 3: Demonstrating the key difference ---");
        
        // Reset and show the critical difference
        @(posedge clk);
        reset_n = 0;
        @(posedge clk);
        reset_n = 1;
        
        // Show what happens when we input '1' after reset
        $display("\nAfter reset, both registers are 00000000");
        $display("Now inputting '1'...");
        
        @(posedge clk);
        serial_in = 1;
        $display("After 1 clock with input='1':");
        $display("  CORRECT:   %8b (1 shifted to bit 7 only)", parallel_out_correct);
        $display("  INCORRECT: %8b (1 propagated through ALL bits!)", parallel_out_incorrect);
        
        @(posedge clk);
        serial_in = 0;
        $display("After 2nd clock with input='0':");
        $display("  CORRECT:   %8b (1 shifted from bit 7 to bit 6)", parallel_out_correct);
        $display("  INCORRECT: %8b (all 0s because 1 'fell out' immediately)", parallel_out_incorrect);
        
        $display("\n--- Analysis Summary ---");
        $display("BLOCKING ASSIGNMENTS (=) PROBLEM:");
        $display("- Execute sequentially within same clock cycle");
        $display("- Each assignment uses the NEW value from previous assignment");
        $display("- Creates 'shift-through' effect - data propagates through ALL stages");
        $display("- Serial input appears at serial output in SAME clock cycle!");
        $display("- NOT a real shift register - just a wire with delay");
        
        $display("\nNON-BLOCKING ASSIGNMENTS (<=) CORRECT:");
        $display("- All assignments scheduled simultaneously");
        $display("- Each assignment uses OLD values from previous clock cycle");
        $display("- Creates proper shift register behavior");
        $display("- Takes 8 clock cycles for serial input to reach serial output");
        $display("- Each bit position stores data for exactly one clock cycle");
        
        $display("\n=== Test Complete ===");
        $display("Examine VCD file to see detailed timing behavior");
        $finish;
    end
    
    // Monitor for educational purposes
    always @(posedge clk) begin
        if (reset_n && shift_enable) begin
            // Show internal register state
            $display("  Internal: Correct[7:0]=%b, Incorrect[7:0]=%b", 
                     SHIFT_REG_INSTANCE.shift_reg_correct, 
                     SHIFT_REG_INSTANCE.shift_reg_incorrect);
        end
    end

endmodule

notebooks/Chapter_6_examples/example_19__shift_register_comparison/shift_register_testbench.vcd
$version Generated by VerilatedVcd $end
$timescale 1ps $end
 $scope module $rootio $end
 $upscope $end
 $scope module shift_register_testbench $end
  $var wire 1 > clk $end
  $var wire 1 3 reset_n $end
  $var wire 1 4 shift_enable $end
  $var wire 1 5 serial_in $end
  $var wire 8 9 parallel_out_correct [7:0] $end
  $var wire 8 : parallel_out_incorrect [7:0] $end
  $var wire 1 ; serial_out_correct $end
  $var wire 1 < serial_out_incorrect $end
  $var wire 1 # test_pattern[0] $end
  $var wire 1 $ test_pattern[1] $end
  $var wire 1 % test_pattern[2] $end
  $var wire 1 & test_pattern[3] $end
  $var wire 1 ' test_pattern[4] $end
  $var wire 1 ( test_pattern[5] $end
  $var wire 1 ) test_pattern[6] $end
  $var wire 1 * test_pattern[7] $end
  $var wire 1 + test_pattern[8] $end
  $var wire 1 , test_pattern[9] $end
  $var wire 1 - test_pattern[10] $end
  $var wire 1 . test_pattern[11] $end
  $var wire 1 / test_pattern[12] $end
  $var wire 1 0 test_pattern[13] $end
  $var wire 1 1 test_pattern[14] $end
  $var wire 1 2 test_pattern[15] $end
  $var wire 32 ? pattern_index [31:0] $end
  $var wire 32 6 cycle_count [31:0] $end
  $scope module SHIFT_REG_INSTANCE $end
   $var wire 1 > clk $end
   $var wire 1 3 reset_n $end
   $var wire 1 4 shift_enable $end
   $var wire 1 5 serial_in $end
   $var wire 8 9 parallel_out_correct [7:0] $end
   $var wire 8 : parallel_out_incorrect [7:0] $end
   $var wire 1 ; serial_out_correct $end
   $var wire 1 < serial_out_incorrect $end
   $var wire 8 9 shift_reg_correct [7:0] $end
   $var wire 8 : shift_reg_incorrect [7:0] $end
   $var wire 8 = shift_reg_concat [7:0] $end
  $upscope $end
  $scope module unnamedblk1 $end
   $var wire 32 7 i [31:0] $end
  $upscope $end
  $scope module unnamedblk2 $end
   $var wire 32 8 i [31:0] $end
  $upscope $end
 $upscope $end
$enddefinitions $end


#0
1#
0$
1%
1&
0'
0(
1)
0*
1+
1,
1-
0.
0/
10
11
02
03
04
05
b00000000000000000000000000000000 6
b00000000000000000000000000000000 7
b00000000000000000000000000000000 8
b00000000 9
b00000000 :
0;
0<
b00000000 =
0>
b00000000000000000000000000000000 ?
#5
1>
#10
0>
#15
13
14
1>
#20
0>
#25
15
b00000000000000000000000000000001 6
b10000000 9
b11111111 :
1<
b10000000 =
1>
#30
0>
#35
05
b00000000000000000000000000000010 6
b00000000000000000000000000000001 7
b01000000 9
b00000000 :
0<
b01000000 =
1>
#40
0>
#45
b00000000000000000000000000000011 6
b00000000000000000000000000000010 7
b00100000 9
b00100000 =
1>
#50
0>
#55
b00000000000000000000000000000100 6
b00000000000000000000000000000011 7
b00010000 9
b00010000 =
1>
#60
0>
#65
b00000000000000000000000000000101 6
b00000000000000000000000000000100 7
b00001000 9
b00001000 =
1>
#70
0>
#75
b00000000000000000000000000000110 6
b00000000000000000000000000000101 7
b00000100 9
b00000100 =
1>
#80
0>
#85
b00000000000000000000000000000111 6
b00000000000000000000000000000110 7
b00000010 9
b00000010 =
1>
#90
0>
#95
b00000000000000000000000000001000 6
b00000000000000000000000000000111 7
b00000001 9
1;
b00000001 =
1>
#100
0>
#105
b00000000000000000000000000001001 6
b00000000000000000000000000001000 7
b00000000 9
0;
b00000000 =
1>
#110
0>
#115
b00000000000000000000000000001010 6
b00000000000000000000000000001001 7
1>
#120
0>
#125
b00000000000000000000000000001011 6
b00000000000000000000000000001010 7
1>
#130
0>
#135
03
1>
#140
0>
#145
13
b00000000000000000000000000000000 6
1>
#150
0>
#155
15
b00000000000000000000000000000001 6
b00000000000000000000000000000001 8
b10000000 9
b11111111 :
1<
b10000000 =
1>
#160
0>
#165
05
b00000000000000000000000000000010 6
b00000000000000000000000000000010 8
b01000000 9
b00000000 :
0<
b01000000 =
1>
#170
0>
#175
15
b00000000000000000000000000000011 6
b00000000000000000000000000000011 8
b10100000 9
b11111111 :
1<
b10100000 =
1>
#180
0>
#185
b00000000000000000000000000000100 6
b00000000000000000000000000000100 8
b11010000 9
b11010000 =
1>
#190
0>
#195
05
b00000000000000000000000000000101 6
b00000000000000000000000000000101 8
b01101000 9
b00000000 :
0<
b01101000 =
1>
#200
0>
#205
b00000000000000000000000000000110 6
b00000000000000000000000000000110 8
b00110100 9
b00110100 =
1>
#210
0>
#215
15
b00000000000000000000000000000111 6
b00000000000000000000000000000111 8
b10011010 9
b11111111 :
1<
b10011010 =
1>
#220
0>
#225
05
b00000000000000000000000000001000 6
b00000000000000000000000000001000 8
b01001101 9
b00000000 :
1;
0<
b01001101 =
1>
#230
0>
#235
15
b00000000000000000000000000001001 6
b00000000000000000000000000001001 8
b10100110 9
b11111111 :
0;
1<
b10100110 =
1>
#240
0>
#245
b00000000000000000000000000001010 6
b00000000000000000000000000001010 8
b11010011 9
1;
b11010011 =
1>
#250
0>
#255
b00000000000000000000000000001011 6
b00000000000000000000000000001011 8
b11101001 9
b11101001 =
1>
#260
0>
#265
05
b00000000000000000000000000001100 6
b00000000000000000000000000001100 8
b01110100 9
b00000000 :
0;
0<
b01110100 =
1>
#270
0>
#275
b00000000000000000000000000001101 6
b00000000000000000000000000001101 8
b00111010 9
b00111010 =
1>
#280
0>
#285
15
b00000000000000000000000000001110 6
b00000000000000000000000000001110 8
b10011101 9
b11111111 :
1;
1<
b10011101 =
1>
#290
0>
#295
b00000000000000000000000000001111 6
b00000000000000000000000000001111 8
b11001110 9
0;
b11001110 =
1>
#300
0>
#305
05
b00000000000000000000000000010000 6
b00000000000000000000000000010000 8
b01100111 9
b00000000 :
1;
0<
b01100111 =
1>
#310
0>
#315
03
b00000000 9
0;
b00000000 =
1>
#320
0>
#325
13
1>
#330
0>
#335
15
b10000000 9
b11111111 :
1<
b10000000 =
1>
#340
0>
#345
05
b01000000 9
b00000000 :
0<
b01000000 =
1>
