notebooks/Chapter_6_examples/example_6__magnitude_comparator/magnitude_comparator.sv
// magnitude_comparator.sv
// Multi-bit Magnitude Comparator
// Compares two N-bit unsigned numbers and generates comparison outputs

module magnitude_comparator #(
    parameter WIDTH = 8  // Bit width of inputs (default 8-bit)
) (
    input  logic [WIDTH-1:0] a_in,    // First number input
    input  logic [WIDTH-1:0] b_in,    // Second number input
    output logic             equal,   // Output: a == b
    output logic             greater, // Output: a > b
    output logic             less     // Output: a < b
);

    // Combinational comparison logic
    always_comb begin
        equal   = (a_in == b_in);
        greater = (a_in > b_in);
        less    = (a_in < b_in);
    end

    // Display comparison results for simulation
    always_comb begin
        if (equal)
            $display("Comparator: %0d == %0d (Equal)", a_in, b_in);
        else if (greater)
            $display("Comparator: %0d > %0d (Greater)", a_in, b_in);
        else if (less)
            $display("Comparator: %0d < %0d (Less)", a_in, b_in);
    end

    // Verification: exactly one output should be high
    always_comb begin
        assert (equal + greater + less == 1) 
        else $error("Comparator error: Multiple or no outputs active!");
    end

endmodule

notebooks/Chapter_6_examples/example_6__magnitude_comparator/magnitude_comparator_testbench.sv
// magnitude_comparator_testbench.sv
module comparator_testbench;

    // Test parameters
    parameter WIDTH = 8;
    
    // Test signals
    logic [WIDTH-1:0] test_a;
    logic [WIDTH-1:0] test_b;
    logic eq_out, gt_out, lt_out;
    
    // Test counters
    int test_count = 0;
    int pass_count = 0;
    int fail_count = 0;

    // Instantiate the design under test
    magnitude_comparator #(.WIDTH(WIDTH)) DUT (
        .a_in(test_a),
        .b_in(test_b),
        .equal(eq_out),
        .greater(gt_out),
        .less(lt_out)
    );

    initial begin
        // Setup waveform dumping
        $dumpfile("comparator_testbench.vcd");
        $dumpvars(0, comparator_testbench);
        
        $display("=== %0d-bit Magnitude Comparator Test ===", WIDTH);
        $display("Testing A vs B with Equal, Greater, Less outputs");
        $display();
        
        // Test 1: Equal values
        $display("Test 1: Equal Values");
        test_equal_values();
        $display();
        
        // Test 2: A greater than B
        $display("Test 2: A > B Cases");
        test_greater_than();
        $display();
        
        // Test 3: A less than B
        $display("Test 3: A < B Cases");
        test_less_than();
        $display();
        
        // Test 4: Edge cases
        $display("Test 4: Edge Cases");
        test_edge_cases();
        $display();
        
        // Test 5: Random comprehensive test
        $display("Test 5: Random Comprehensive Test");
        test_random_values();
        $display();
        
        // Final summary
        $display("=== Test Summary ===");
        $display("Total tests: %0d", test_count);
        $display("Passed: %0d", pass_count);
        $display("Failed: %0d", fail_count);
        if (fail_count == 0) begin
            $display("ALL TESTS PASSED!");
        end else begin
            $display("%0d TESTS FAILED", fail_count);
        end
        
        $finish;
    end

    // Task to test equal values
    task automatic test_equal_values();
        logic [WIDTH-1:0] test_values [5];
        
        // Initialize test values
        test_values[0] = 0;
        test_values[1] = 1;
        test_values[2] = 15;
        test_values[3] = 128;
        test_values[4] = 255;
        
        foreach (test_values[i]) begin
            test_a = test_values[i];
            test_b = test_values[i];
            #10;
            verify_result(1, 0, 0, "Equal");
        end
    endtask

    // Task to test A > B cases
    task automatic test_greater_than();
        // Test arrays for A > B cases
        logic [WIDTH-1:0] test_a_vals [5] = '{10, 255, 128, 100, 200};
        logic [WIDTH-1:0] test_b_vals [5] = '{5, 254, 127, 50, 199};
        
        for (int i = 0; i < 5; i++) begin
            test_a = test_a_vals[i];
            test_b = test_b_vals[i];
            #10;
            verify_result(0, 1, 0, "Greater");
        end
    endtask

    // Task to test A < B cases
    task automatic test_less_than();
        // Test arrays for A < B cases
        logic [WIDTH-1:0] test_a_vals [5] = '{5, 0, 127, 50, 199};
        logic [WIDTH-1:0] test_b_vals [5] = '{10, 1, 128, 100, 200};
        
        for (int i = 0; i < 5; i++) begin
            test_a = test_a_vals[i];
            test_b = test_b_vals[i];
            #10;
            verify_result(0, 0, 1, "Less");
        end
    endtask

    // Task to test edge cases
    task automatic test_edge_cases();
        // Minimum values
        test_a = 0; test_b = 0;
        #10; verify_result(1, 0, 0, "Min Equal");
        
        // Maximum values
        test_a = {WIDTH{1'b1}}; test_b = {WIDTH{1'b1}};
        #10; verify_result(1, 0, 0, "Max Equal");
        
        // Min vs Max
        test_a = 0; test_b = {WIDTH{1'b1}};
        #10; verify_result(0, 0, 1, "Min < Max");
        
        // Max vs Min
        test_a = {WIDTH{1'b1}}; test_b = 0;
        #10; verify_result(0, 1, 0, "Max > Min");
        
        // Adjacent values
        test_a = 100; test_b = 101;
        #10; verify_result(0, 0, 1, "Adjacent Less");
        
        test_a = 101; test_b = 100;
        #10; verify_result(0, 1, 0, "Adjacent Greater");
    endtask

    // Task for random testing
    task automatic test_random_values();
        logic [31:0] rand_val;
        
        for (int i = 0; i < 20; i++) begin
            // Generate random values with proper bit width
            rand_val = $random();
            test_a = rand_val[WIDTH-1:0];
            rand_val = $random();
            test_b = rand_val[WIDTH-1:0];
            #10;
            
            // Determine expected result
            if (test_a == test_b)
                verify_result(1, 0, 0, "Random Equal");
            else if (test_a > test_b)
                verify_result(0, 1, 0, "Random Greater");
            else
                verify_result(0, 0, 1, "Random Less");
        end
    endtask

    // Verification task
    task automatic verify_result(logic exp_eq, logic exp_gt, logic exp_lt, string test_name);
        test_count++;
        
        if (eq_out == exp_eq && gt_out == exp_gt && lt_out == exp_lt) begin
            pass_count++;
            $display(
                "%s: A=%0d, B=%0d -> EQ=%b GT=%b LT=%b", 
                test_name, test_a, test_b, eq_out, gt_out, lt_out);
        end else begin
            fail_count++;
            $display(
                "%s: A=%0d, B=%0d -> Expected: EQ=%b GT=%b LT=%b, Got: EQ=%b GT=%b LT=%b", 
                test_name, test_a, test_b, exp_eq, exp_gt, exp_lt, eq_out, gt_out, lt_out);
        end
    endtask

    // Monitor for timing analysis
    always @(test_a or test_b) begin
        #1; // Small delay to let outputs settle
        // Check that exactly one output is active
        if ((eq_out + gt_out + lt_out) != 1) begin
            $display(
                "WARNING: Invalid output state at A=%0d, B=%0d",
                test_a, test_b);
        end
    end

    // Performance analysis
    initial begin
        #1000; // Wait for all tests to complete
        $display();
        $display("=== Performance Analysis ===");
        $display("Comparator width: %0d bits", WIDTH);
        $display("Maximum input value: %0d", (2**WIDTH)-1);
        $display("Total possible comparisons: %0d", (2**WIDTH) * (2**WIDTH));
        $display("Tests performed: %0d (%.2f%% coverage)", 
                test_count,
                (real'(test_count) / real'((2**WIDTH) * (2**WIDTH))) * 100.0);
    end

endmodule

notebooks/Chapter_6_examples/example_6__magnitude_comparator/comparator_testbench.vcd
$version Generated by VerilatedVcd $end
$timescale 1ps $end
 $scope module $rootio $end
 $upscope $end
 $scope module comparator_testbench $end
  $var wire 32 + WIDTH [31:0] $end
  $var wire 8 # test_a [7:0] $end
  $var wire 8 $ test_b [7:0] $end
  $var wire 1 % eq_out $end
  $var wire 1 & gt_out $end
  $var wire 1 ' lt_out $end
  $var wire 32 ( test_count [31:0] $end
  $var wire 32 ) pass_count [31:0] $end
  $var wire 32 * fail_count [31:0] $end
  $scope module DUT $end
   $var wire 32 + WIDTH [31:0] $end
   $var wire 8 # a_in [7:0] $end
   $var wire 8 $ b_in [7:0] $end
   $var wire 1 % equal $end
   $var wire 1 & greater $end
   $var wire 1 ' less $end
  $upscope $end
 $upscope $end
$enddefinitions $end


#0
b00000000 #
b00000000 $
1%
0&
0'
b00000000000000000000000000000000 (
b00000000000000000000000000000000 )
b00000000000000000000000000000000 *
b00000000000000000000000000001000 +
#10
b00000001 #
b00000001 $
b00000000000000000000000000000001 (
b00000000000000000000000000000001 )
#20
b00001111 #
b00001111 $
b00000000000000000000000000000010 (
b00000000000000000000000000000010 )
#30
b10000000 #
b10000000 $
b00000000000000000000000000000011 (
b00000000000000000000000000000011 )
#40
b11111111 #
b11111111 $
b00000000000000000000000000000100 (
b00000000000000000000000000000100 )
#50
b00001010 #
b00000101 $
0%
1&
b00000000000000000000000000000101 (
b00000000000000000000000000000101 )
#60
b11111111 #
b11111110 $
b00000000000000000000000000000110 (
b00000000000000000000000000000110 )
#70
b10000000 #
b01111111 $
b00000000000000000000000000000111 (
b00000000000000000000000000000111 )
#80
b01100100 #
b00110010 $
b00000000000000000000000000001000 (
b00000000000000000000000000001000 )
#90
b11001000 #
b11000111 $
b00000000000000000000000000001001 (
b00000000000000000000000000001001 )
#100
b00000101 #
b00001010 $
0&
1'
b00000000000000000000000000001010 (
b00000000000000000000000000001010 )
#110
b00000000 #
b00000001 $
b00000000000000000000000000001011 (
b00000000000000000000000000001011 )
#120
b01111111 #
b10000000 $
b00000000000000000000000000001100 (
b00000000000000000000000000001100 )
#130
b00110010 #
b01100100 $
b00000000000000000000000000001101 (
b00000000000000000000000000001101 )
#140
b11000111 #
b11001000 $
b00000000000000000000000000001110 (
b00000000000000000000000000001110 )
#150
b00000000 #
b00000000 $
1%
0'
b00000000000000000000000000001111 (
b00000000000000000000000000001111 )
#160
b11111111 #
b11111111 $
b00000000000000000000000000010000 (
b00000000000000000000000000010000 )
#170
b00000000 #
0%
1'
b00000000000000000000000000010001 (
b00000000000000000000000000010001 )
#180
b11111111 #
b00000000 $
1&
0'
b00000000000000000000000000010010 (
b00000000000000000000000000010010 )
#190
b01100100 #
b01100101 $
0&
1'
b00000000000000000000000000010011 (
b00000000000000000000000000010011 )
#200
b01100101 #
b01100100 $
1&
0'
b00000000000000000000000000010100 (
b00000000000000000000000000010100 )
#210
b11000100 #
b10011100 $
b00000000000000000000000000010101 (
b00000000000000000000000000010101 )
#220
b00000010 #
b11100100 $
0&
1'
b00000000000000000000000000010110 (
b00000000000000000000000000010110 )
#230
b01111000 #
b10111100 $
b00000000000000000000000000010111 (
b00000000000000000000000000010111 )
#240
b10110110 #
b11100100 $
b00000000000000000000000000011000 (
b00000000000000000000000000011000 )
#250
b10110111 #
b01010011 $
1&
0'
b00000000000000000000000000011001 (
b00000000000000000000000000011001 )
#260
b00100001 #
b11100001 $
0&
1'
b00000000000000000000000000011010 (
b00000000000000000000000000011010 )
#270
b11000101 #
b10000010 $
1&
0'
b00000000000000000000000000011011 (
b00000000000000000000000000011011 )
#280
b01100010 #
b00110101 $
b00000000000000000000000000011100 (
b00000000000000000000000000011100 )
#290
b00010010 #
b01010110 $
0&
1'
b00000000000000000000000000011101 (
b00000000000000000000000000011101 )
#300
b11111101 #
b11110100 $
1&
0'
b00000000000000000000000000011110 (
b00000000000000000000000000011110 )
#310
b00111011 #
b01011000 $
0&
1'
b00000000000000000000000000011111 (
b00000000000000000000000000011111 )
#320
b10110010 #
b01011100 $
1&
0'
b00000000000000000000000000100000 (
b00000000000000000000000000100000 )
#330
b00011110 #
b10011110 $
0&
1'
b00000000000000000000000000100001 (
b00000000000000000000000000100001 )
#340
b10011110 #
b11101110 $
b00000000000000000000000000100010 (
b00000000000000000000000000100010 )
#350
b00010000 #
b01110110 $
b00000000000000000000000000100011 (
b00000000000000000000000000100011 )
#360
b01100011 #
b11000000 $
b00000000000000000000000000100100 (
b00000000000000000000000000100100 )
#370
b00011101 #
b00100010 $
b00000000000000000000000000100101 (
b00000000000000000000000000100101 )
#380
b00000110 #
b10000001 $
b00000000000000000000000000100110 (
b00000000000000000000000000100110 )
#390
b01100011 #
b01111000 $
b00000000000000000000000000100111 (
b00000000000000000000000000100111 )
#400
b01101111 #
b11001110 $
b00000000000000000000000000101000 (
b00000000000000000000000000101000 )
#410
b00000000000000000000000000101001 (
b00000000000000000000000000101001 )
