notebooks/Chapter_7_examples/example_36__assertion_functions/simple_counter_design.sv
// simple_counter_design.sv
module simple_counter_module (
  input  logic       clock_signal,
  input  logic       reset_signal,
  input  logic       enable_signal,
  output logic [3:0] counter_output
);

  always_ff @(posedge clock_signal or posedge reset_signal) begin
    if (reset_signal) begin
      counter_output <= 4'b0000;
    end
    else if (enable_signal) begin
      counter_output <= counter_output + 1;
    end
  end

endmodule

notebooks/Chapter_7_examples/example_36__assertion_functions/simple_counter_design_testbench.sv
// simple_counter_design_testbench.sv
module counter_assertion_testbench;

  // Test signals
  logic       clock_signal;
  logic       reset_signal;
  logic       enable_signal;
  logic [3:0] counter_output;
  
  // Test statistics
  int         passed_assertion_count = 0;
  int         failed_assertion_count = 0;

  // Instantiate design under test
  simple_counter_module COUNTER_INSTANCE (
    .clock_signal(clock_signal),
    .reset_signal(reset_signal),
    .enable_signal(enable_signal),
    .counter_output(counter_output)
  );

  // Clock generation
  initial begin
    clock_signal = 0;
    forever #5 clock_signal = ~clock_signal;
  end

  // Assertion function for equality check
  function void assert_equals_function(
    input logic [3:0] expected_value,
    input logic [3:0] actual_value,
    input string      test_description
  );
    if (expected_value === actual_value) begin
      $display("[PASS] %s: Expected=%0d, Actual=%0d", 
               test_description, expected_value, actual_value);
      passed_assertion_count++;
    end
    else begin
      $display("[FAIL] %s: Expected=%0d, Actual=%0d", 
               test_description, expected_value, actual_value);
      failed_assertion_count++;
    end
  endfunction

  // Assertion function for reset state verification
  function void assert_reset_state_function(
    input logic [3:0] counter_value,
    input string      test_phase
  );
    if (counter_value === 4'b0000) begin
      $display("[PASS] Reset State Check (%s): Counter = %0d", 
               test_phase, counter_value);
      passed_assertion_count++;
    end
    else begin
      $display("[FAIL] Reset State Check (%s): Counter = %0d (should be 0)", 
               test_phase, counter_value);
      failed_assertion_count++;
    end
  endfunction

  // Assertion function for range validation
  function void assert_counter_range_function(
    input logic [3:0] counter_value,
    input logic [3:0] min_value,
    input logic [3:0] max_value,
    input string      test_context
  );
    if (counter_value >= min_value && counter_value <= max_value) begin
      $display("[PASS] Range Check (%s): Counter=%0d within [%0d:%0d]", 
               test_context, counter_value, min_value, max_value);
      passed_assertion_count++;
    end
    else begin
      $display("[FAIL] Range Check (%s): Counter=%0d outside [%0d:%0d]", 
               test_context, counter_value, min_value, max_value);
      failed_assertion_count++;
    end
  endfunction

  // Test summary function
  function void display_test_summary_function();
    $display();
    $display("=== TEST SUMMARY ===");
    $display("Passed Assertions: %0d", passed_assertion_count);
    $display("Failed Assertions: %0d", failed_assertion_count);
    $display("Total Assertions:  %0d", 
             passed_assertion_count + failed_assertion_count);
    if (failed_assertion_count == 0)
      $display("*** ALL TESTS PASSED ***");
    else
      $display("*** %0d TESTS FAILED ***", failed_assertion_count);
    $display();
  endfunction

  // Main test sequence
  initial begin
    // Dump waves
    $dumpfile("counter_assertion_testbench.vcd");
    $dumpvars(0, counter_assertion_testbench);
    
    $display("=== Starting Assertion Functions Test ===");
    $display();
    
    // Initialize signals
    reset_signal = 1;
    enable_signal = 0;
    
    // Test 1: Reset functionality
    #10;
    assert_reset_state_function(counter_output, "Initial Reset");
    
    // Test 2: Release reset
    reset_signal = 0;
    #10;
    assert_equals_function(4'd0, counter_output, "After Reset Release");
    
    // Test 3: Enable counter and check increments
    enable_signal = 1;
    #10;
    assert_equals_function(4'd1, counter_output, "First Increment");
    
    #10;
    assert_equals_function(4'd2, counter_output, "Second Increment");
    
    #10;
    assert_equals_function(4'd3, counter_output, "Third Increment");
    
    // Test 4: Range validation during counting
    assert_counter_range_function(counter_output, 4'd0, 4'd15, 
                                  "Normal Count Range");
    
    // Test 5: Disable counter
    enable_signal = 0;
    #20;
    assert_equals_function(4'd3, counter_output, "Counter Disabled");
    
    // Test 6: Re-enable and continue
    enable_signal = 1;
    #10;
    assert_equals_function(4'd4, counter_output, "Re-enabled Counter");
    
    // Test 7: Reset during operation
    reset_signal = 1;
    #10;
    assert_reset_state_function(counter_output, "Reset During Operation");
    
    // Test 8: Counter overflow test (let it count to maximum)
    reset_signal = 0;
    enable_signal = 1;
    
    // Wait for counter to reach maximum value
    repeat(16) #10;
    
    // Check if counter wraps around correctly
    assert_counter_range_function(counter_output, 4'd0, 4'd15, 
                                  "After Overflow");
    
    // Display final test summary
    #10;
    display_test_summary_function();
    
    $finish;
  end

endmodule

notebooks/Chapter_7_examples/example_36__assertion_functions/counter_assertion_testbench.vcd
$version Generated by VerilatedVcd $end
$timescale 1ps $end
 $scope module $rootio $end
 $upscope $end
 $scope module counter_assertion_testbench $end
  $var wire 1 # clock_signal $end
  $var wire 1 $ reset_signal $end
  $var wire 1 % enable_signal $end
  $var wire 4 & counter_output [3:0] $end
  $var wire 32 ' passed_assertion_count [31:0] $end
  $var wire 32 ( failed_assertion_count [31:0] $end
  $scope module COUNTER_INSTANCE $end
   $var wire 1 # clock_signal $end
   $var wire 1 $ reset_signal $end
   $var wire 1 % enable_signal $end
   $var wire 4 & counter_output [3:0] $end
  $upscope $end
 $upscope $end
$enddefinitions $end


#0
0#
1$
0%
b0000 &
b00000000000000000000000000000000 '
b00000000000000000000000000000000 (
#5
1#
#10
0#
0$
b00000000000000000000000000000001 '
#15
1#
#20
0#
1%
b00000000000000000000000000000010 '
#25
1#
b0001 &
#30
0#
b00000000000000000000000000000011 '
#35
1#
b0010 &
#40
0#
b00000000000000000000000000000100 '
#45
1#
b0011 &
#50
0#
0%
b00000000000000000000000000000110 '
#55
1#
#60
0#
#65
1#
#70
0#
1%
b00000000000000000000000000000111 '
#75
1#
b0100 &
#80
0#
1$
b0000 &
b00000000000000000000000000001000 '
#85
1#
#90
0#
0$
b00000000000000000000000000001001 '
#95
1#
b0001 &
#100
0#
#105
1#
b0010 &
#110
0#
#115
1#
b0011 &
#120
0#
#125
1#
b0100 &
#130
0#
#135
1#
b0101 &
#140
0#
#145
1#
b0110 &
#150
0#
#155
1#
b0111 &
#160
0#
#165
1#
b1000 &
#170
0#
#175
1#
b1001 &
#180
0#
#185
1#
b1010 &
#190
0#
#195
1#
b1011 &
#200
0#
#205
1#
b1100 &
#210
0#
#215
1#
b1101 &
#220
0#
#225
1#
b1110 &
#230
0#
#235
1#
b1111 &
#240
0#
#245
1#
b0000 &
#250
0#
b00000000000000000000000000001010 '
#255
1#
b0001 &
