notebooks/Chapter_7_examples/example_16__waveform_generator_task/waveform_generator_design.sv
// waveform_generator_design.sv
module waveform_generator_module (
  input  logic       clock_signal,
  input  logic       reset_signal,
  input  logic [1:0] waveform_type_select,
  output logic       generated_waveform_output
);

  logic [3:0] internal_counter;
  
  // Counter for waveform generation
  always_ff @(posedge clock_signal or posedge reset_signal) begin
    if (reset_signal) begin
      internal_counter <= 4'h0;
    end else begin
      internal_counter <= internal_counter + 1'b1;
    end
  end
  
  // Waveform generation based on type selection
  always_comb begin
    case (waveform_type_select)
      2'b00: // Square wave (50% duty cycle)
        generated_waveform_output = internal_counter[3];
      2'b01: // Triangle wave approximation (using counter bits)
        generated_waveform_output = internal_counter[2] ^ internal_counter[3];
      2'b10: // Sawtooth wave (using MSB)
        generated_waveform_output = internal_counter[3];
      2'b11: // Pulse wave (25% duty cycle)
        generated_waveform_output = (internal_counter < 4'h4);
      default:
        generated_waveform_output = 1'b0;
    endcase
  end

endmodule

notebooks/Chapter_7_examples/example_16__waveform_generator_task/waveform_generator_design_testbench.sv
// waveform_generator_design_testbench.sv
module waveform_generator_testbench;
  
  // Testbench signals
  logic       clock_signal;
  logic       reset_signal;
  logic [1:0] waveform_type_select;
  logic       generated_waveform_output;
  
  // Instantiate design under test
  waveform_generator_module WAVEFORM_GENERATOR_INSTANCE (
    .clock_signal(clock_signal),
    .reset_signal(reset_signal),
    .waveform_type_select(waveform_type_select),
    .generated_waveform_output(generated_waveform_output)
  );
  
  // Clock generation
  initial begin
    clock_signal = 1'b0;
    forever #5 clock_signal = ~clock_signal;
  end
  
  // Task to generate different waveform types
  task automatic generate_waveform_pattern(
    input [1:0] selected_waveform_type,
    input int   pattern_duration_cycles
  );
    $display("Generating waveform type: %0d for %0d cycles", 
             selected_waveform_type, pattern_duration_cycles);
    waveform_type_select = selected_waveform_type;
    repeat(pattern_duration_cycles) @(posedge clock_signal);
    $display("Waveform pattern generation completed");
    $display();
  endtask
  
  // Task to apply reset sequence
  task automatic apply_system_reset(input int reset_duration_cycles);
    $display("Applying system reset for %0d cycles", reset_duration_cycles);
    reset_signal = 1'b1;
    repeat(reset_duration_cycles) @(posedge clock_signal);
    reset_signal = 1'b0;
    $display("System reset released");
    $display();
  endtask
  
  // Main test sequence
  initial begin
    // Setup waveform dumping
    $dumpfile("waveform_generator_testbench.vcd");
    $dumpvars(0, waveform_generator_testbench);
    
    // Initialize signals
    reset_signal = 1'b0;
    waveform_type_select = 2'b00;
    
    $display();
    $display("=== Waveform Generator Task Test ===");
    $display();
    
    // Apply reset
    apply_system_reset(3);
    
    // Test different waveform types using tasks
    generate_waveform_pattern(2'b00, 16);  // Square wave
    generate_waveform_pattern(2'b01, 16);  // Triangle wave
    generate_waveform_pattern(2'b10, 16);  // Sawtooth wave
    generate_waveform_pattern(2'b11, 16);  // Pulse wave
    
    $display("All waveform patterns tested successfully!");
    $display();
    
    #50;
    $finish;
  end
  
endmodule

notebooks/Chapter_7_examples/example_16__waveform_generator_task/waveform_generator_testbench.vcd
$version Generated by VerilatedVcd $end
$timescale 1ps $end
 $scope module $rootio $end
 $upscope $end
 $scope module waveform_generator_testbench $end
  $var wire 1 # clock_signal $end
  $var wire 1 $ reset_signal $end
  $var wire 2 % waveform_type_select [1:0] $end
  $var wire 1 & generated_waveform_output $end
  $scope module WAVEFORM_GENERATOR_INSTANCE $end
   $var wire 1 # clock_signal $end
   $var wire 1 $ reset_signal $end
   $var wire 2 % waveform_type_select [1:0] $end
   $var wire 1 & generated_waveform_output $end
   $var wire 4 ' internal_counter [3:0] $end
  $upscope $end
 $upscope $end
$enddefinitions $end


#0
0#
1$
b00 %
0&
b0000 '
#5
1#
#10
0#
#15
1#
#20
0#
#25
1#
0$
b0001 '
#30
0#
#35
1#
b0010 '
#40
0#
#45
1#
b0011 '
#50
0#
#55
1#
b0100 '
#60
0#
#65
1#
b0101 '
#70
0#
#75
1#
b0110 '
#80
0#
#85
1#
b0111 '
#90
0#
#95
1#
1&
b1000 '
#100
0#
#105
1#
b1001 '
#110
0#
#115
1#
b1010 '
#120
0#
#125
1#
b1011 '
#130
0#
#135
1#
b1100 '
#140
0#
#145
1#
b1101 '
#150
0#
#155
1#
b1110 '
#160
0#
#165
1#
b1111 '
#170
0#
#175
1#
0&
b0000 '
#180
0#
#185
1#
b01 %
b0001 '
#190
0#
#195
1#
b0010 '
#200
0#
#205
1#
b0011 '
#210
0#
#215
1#
1&
b0100 '
#220
0#
#225
1#
b0101 '
#230
0#
#235
1#
b0110 '
#240
0#
#245
1#
b0111 '
#250
0#
#255
1#
b1000 '
#260
0#
#265
1#
b1001 '
#270
0#
#275
1#
b1010 '
#280
0#
#285
1#
b1011 '
#290
0#
#295
1#
0&
b1100 '
#300
0#
#305
1#
b1101 '
#310
0#
#315
1#
b1110 '
#320
0#
#325
1#
b1111 '
#330
0#
#335
1#
b0000 '
#340
0#
#345
1#
b10 %
b0001 '
#350
0#
#355
1#
b0010 '
#360
0#
#365
1#
b0011 '
#370
0#
#375
1#
b0100 '
#380
0#
#385
1#
b0101 '
#390
0#
#395
1#
b0110 '
#400
0#
#405
1#
b0111 '
#410
0#
#415
1#
1&
b1000 '
#420
0#
#425
1#
b1001 '
#430
0#
#435
1#
b1010 '
#440
0#
#445
1#
b1011 '
#450
0#
#455
1#
b1100 '
#460
0#
#465
1#
b1101 '
#470
0#
#475
1#
b1110 '
#480
0#
#485
1#
b1111 '
#490
0#
#495
1#
0&
b0000 '
#500
0#
#505
1#
b11 %
1&
b0001 '
#510
0#
#515
1#
b0010 '
#520
0#
#525
1#
b0011 '
#530
0#
#535
1#
0&
b0100 '
#540
0#
#545
1#
b0101 '
#550
0#
#555
1#
b0110 '
#560
0#
#565
1#
b0111 '
#570
0#
#575
1#
b1000 '
#580
0#
#585
1#
b1001 '
#590
0#
#595
1#
b1010 '
#600
0#
#605
1#
b1011 '
#610
0#
#615
1#
b1100 '
#620
0#
#625
1#
b1101 '
#630
0#
#635
1#
b1110 '
#640
0#
#645
1#
b1111 '
#650
0#
#655
1#
1&
b0000 '
#660
0#
#665
1#
b0001 '
#670
0#
#675
1#
b0010 '
#680
0#
#685
1#
b0011 '
#690
0#
#695
1#
0&
b0100 '
#700
0#
#705
1#
b0101 '
#710
0#
#715
1#
b0110 '
