notebooks/Chapter_6_examples/example_3__priority_encoder/priority_encoder_8to3.sv
// priority_encoder_8to3.sv
module priority_encoder_8to3 (
    input  logic [7:0] data_in,     // 8-bit input data
    output logic [2:0] encoded_out, // 3-bit encoded output
    output logic       valid_out    // Valid signal (any input active)
);

    // Priority encoder logic - highest bit wins
    always_comb begin
        if (data_in[7]) begin
            encoded_out = 3'b111;       // Input 7 has highest priority
            valid_out = 1'b1;
        end else if (data_in[6]) begin
            encoded_out = 3'b110;       // Input 6
            valid_out = 1'b1;
        end else if (data_in[5]) begin
            encoded_out = 3'b101;       // Input 5
            valid_out = 1'b1;
        end else if (data_in[4]) begin
            encoded_out = 3'b100;       // Input 4
            valid_out = 1'b1;
        end else if (data_in[3]) begin
            encoded_out = 3'b011;       // Input 3
            valid_out = 1'b1;
        end else if (data_in[2]) begin
            encoded_out = 3'b010;       // Input 2
            valid_out = 1'b1;
        end else if (data_in[1]) begin
            encoded_out = 3'b001;       // Input 1
            valid_out = 1'b1;
        end else if (data_in[0]) begin
            encoded_out = 3'b000;       // Input 0 (lowest priority)
            valid_out = 1'b1;
        end else begin
            encoded_out = 3'b000;       // No inputs active
            valid_out = 1'b0;
        end
    end

    // Display encoder operation
    always_comb begin
        if (valid_out) begin
            $display("Priority Encoder: Input=%8b -> Encoded=%3b (%0d), Valid=%b", 
                     data_in, encoded_out, encoded_out, valid_out);
        end else begin
            $display("Priority Encoder: Input=%8b -> No valid input (Valid=%b)", 
                     data_in, valid_out);
        end
    end

endmodule

notebooks/Chapter_6_examples/example_3__priority_encoder/priority_encoder_8to3_testbench.sv
// priority_encoder_8to3_testbench.sv
module priority_encoder_testbench;

    // Test signals
    logic [7:0] test_data_in;
    logic [2:0] encoded_result;
    logic       valid_result;

    // Instantiate the design under test
    priority_encoder_8to3 DUT (
        .data_in(test_data_in),
        .encoded_out(encoded_result),
        .valid_out(valid_result)
    );

    initial begin
        // Setup waveform dumping
        $dumpfile("priority_encoder_testbench.vcd");
        $dumpvars(0, priority_encoder_testbench);
        
        $display("=== 8-to-3 Priority Encoder Test ===");
        $display();
        
        // Test 1: No inputs active
        $display("Test 1: No inputs active");
        test_data_in = 8'b00000000;
        #10;
        
        $display();
        
        // Test 2: Single bit tests (test each priority level)
        $display("Test 2: Testing each input individually");
        for (int i = 0; i < 8; i++) begin
            test_data_in = 8'b00000001 << i;
            #10;
            
            // Verify correct encoding
            if (valid_result && (encoded_result == i[2:0])) begin
                $display("Input bit %0d correctly encoded", i);
            end else begin
                $display("ERROR: Input bit %0d encoding failed!", i);
            end
        end
        
        $display();
        
        // Test 3: Priority tests (multiple bits active)
        $display("Test 3: Testing priority behavior");
        
        // High priority wins over low priority
        test_data_in = 8'b10000001; // Bit 7 and 0 active
        #10;
        if (encoded_result == 3'b111) begin
            $display("Bit 7 correctly wins over bit 0");
        end else begin
            $display("ERROR: Priority not working correctly!");
        end
        
        // Middle priority test
        test_data_in = 8'b00101010; // Bits 5, 3, 1 active
        #10;
        if (encoded_result == 3'b101) begin
            $display("Bit 5 correctly wins over bits 3,1");
        end else begin
            $display("ERROR: Middle priority test failed!");
        end
        
        // All bits active (highest should win)
        test_data_in = 8'b11111111;
        #10;
        if (encoded_result == 3'b111) begin
            $display("Bit 7 correctly wins when all bits active");
        end else begin
            $display("ERROR: All bits test failed!");
        end
        
        $display();
        
        // Test 4: Random priority patterns
        $display("Test 4: Testing various priority patterns");
        
        test_data_in = 8'b01100000; // Bits 6,5 active -> 6 wins
        #10;
        
        test_data_in = 8'b00011100; // Bits 4,3,2 active -> 4 wins
        #10;
        
        test_data_in = 8'b00000110; // Bits 2,1 active -> 2 wins
        #10;
        
        $display();
        $display("=== Priority Encoder Test Complete ===");
        $display("Priority order: Bit 7 (highest) down to Bit 0 (lowest)");
        $display("Valid signal: Indicates at least one input is active");
        $display("Encoding: Highest priority active input -> binary output");
        $display();
        
        $finish;
    end

    // Monitor for unexpected behavior
    always @(test_data_in) begin
        #1; // Small delay to let combinational logic settle
        if (test_data_in != 8'b00000000 && !valid_result) begin
            $display("WARNING: Valid should be high when inputs are active!");
        end
        if (test_data_in == 8'b00000000 && valid_result) begin
            $display("WARNING: Valid should be low when no inputs active!");
        end
    end

endmodule

notebooks/Chapter_6_examples/example_3__priority_encoder/priority_encoder_testbench.vcd
$version Generated by VerilatedVcd $end
$timescale 1ps $end
 $scope module $rootio $end
 $upscope $end
 $scope module priority_encoder_testbench $end
  $var wire 8 # test_data_in [7:0] $end
  $var wire 3 $ encoded_result [2:0] $end
  $var wire 1 % valid_result $end
  $scope module DUT $end
   $var wire 8 # data_in [7:0] $end
   $var wire 3 $ encoded_out [2:0] $end
   $var wire 1 % valid_out $end
  $upscope $end
  $scope module unnamedblk1 $end
   $var wire 32 & i [31:0] $end
  $upscope $end
 $upscope $end
$enddefinitions $end


#0
b00000000 #
b000 $
0%
b00000000000000000000000000000000 &
#10
b00000001 #
1%
#20
b00000010 #
b001 $
b00000000000000000000000000000001 &
#30
b00000100 #
b010 $
b00000000000000000000000000000010 &
#40
b00001000 #
b011 $
b00000000000000000000000000000011 &
#50
b00010000 #
b100 $
b00000000000000000000000000000100 &
#60
b00100000 #
b101 $
b00000000000000000000000000000101 &
#70
b01000000 #
b110 $
b00000000000000000000000000000110 &
#80
b10000000 #
b111 $
b00000000000000000000000000000111 &
#90
b10000001 #
b00000000000000000000000000001000 &
#100
b00101010 #
b101 $
#110
b11111111 #
b111 $
#120
b01100000 #
b110 $
#130
b00011100 #
b100 $
#140
b00000110 #
b010 $
