notebooks/chapter_11_examples/example_10__universal_cache/universal_cache.sv
module universal_cache #(
    parameter int unsigned KEY_WIDTH = 8,
    parameter int unsigned VALUE_WIDTH = 8,
    parameter int unsigned CACHE_SIZE = 4
) (
    input logic clk,
    input logic rst,
    input logic [KEY_WIDTH-1:0] key,
    input logic [VALUE_WIDTH-1:0] value,
    input logic put,
    output logic [VALUE_WIDTH-1:0] output_value,
    output logic hit
);

logic [CACHE_SIZE-1:0][KEY_WIDTH-1:0] cache_keys;
logic [CACHE_SIZE-1:0][VALUE_WIDTH-1:0] cache_values;

always_ff @(posedge clk or posedge rst) begin
    if (rst) begin
        cache_keys <= 0;
        cache_values <= 0;
    end else begin
        if (put) begin
            cache_keys[0] <= key;
            cache_values[0] <= value;
            for (int i = 1; i < CACHE_SIZE; i++) begin
                cache_keys[i] <= cache_keys[i-1];
                cache_values[i] <= cache_values[i-1];
            end
        end
    end
end

always_comb begin
    hit = 0;
    output_value = 0;
    for (int i = 0; i < CACHE_SIZE; i++) begin
        if (cache_keys[i] == key) begin
            hit = 1;
            output_value = cache_values[i];
            break;
        end
    end
end

endmodule

notebooks/chapter_11_examples/example_10__universal_cache/universal_cache_tb.sv
module universal_cache_tb;

logic clk;
logic rst;
logic [7:0] key;
logic [7:0] value;
logic put;
logic [7:0] output_value;
logic hit;

universal_cache #(.KEY_WIDTH(8), .VALUE_WIDTH(8), .CACHE_SIZE(4)) dut (
    .clk(clk),
    .rst(rst),
    .key(key),
    .value(value),
    .put(put),
    .output_value(output_value),
    .hit(hit)
);

initial begin
    $dumpfile("universal_cache_tb.vcd");
    $dumpvars(0, universal_cache_tb);
end

initial begin
    clk = 0;
    forever #5 clk = ~clk;
end

initial begin
    rst = 1;
    #10 rst = 0;
    $display("=== Universal Cache Testbench Started ===");

    $display("Testing cache put/get...");
    key = 1;
    value = 10;
    put = 1;
    #10 put = 0;
    #10 key = 2;
    #10 value = 20;
    put = 1;
    #10 put = 0;
    #10 key = 1;
    #10 if (output_value != 10) $display("Error: cache get failed");
    else $display("Test cache put/get: PASSED");

    $display("Testing cache hit...");
    key = 2;
    #10 if (hit != 1) $display("Error: cache hit failed");
    else $display("Test cache hit: PASSED");

    $display("Testing cache miss...");
    key = 3;
    #10 if (hit != 0) $display("Error: cache miss failed");
    else $display("Test cache miss: PASSED");

    $display("=== Testbench Completed ===");
    #10 $finish;
end

endmodule

notebooks/chapter_11_examples/example_10__universal_cache/universal_cache_tb.vcd
$version Generated by VerilatedVcd $end
$timescale 1ps $end
 $scope module $rootio $end
 $upscope $end
 $scope module universal_cache_tb $end
  $var wire 1 & clk $end
  $var wire 1 ' rst $end
  $var wire 8 ( key [7:0] $end
  $var wire 8 ) value [7:0] $end
  $var wire 1 * put $end
  $var wire 8 + output_value [7:0] $end
  $var wire 1 , hit $end
  $scope module dut $end
   $var wire 32 . KEY_WIDTH [31:0] $end
   $var wire 32 . VALUE_WIDTH [31:0] $end
   $var wire 32 / CACHE_SIZE [31:0] $end
   $var wire 1 & clk $end
   $var wire 1 ' rst $end
   $var wire 8 ( key [7:0] $end
   $var wire 8 ) value [7:0] $end
   $var wire 1 * put $end
   $var wire 8 + output_value [7:0] $end
   $var wire 1 , hit $end
   $var wire 32 # cache_keys [31:0] $end
   $var wire 32 $ cache_values [31:0] $end
   $scope module unnamedblk1 $end
    $var wire 32 % i [31:0] $end
   $upscope $end
   $scope module unnamedblk2 $end
    $var wire 32 - i [31:0] $end
   $upscope $end
  $upscope $end
 $upscope $end
$enddefinitions $end


#0
b00000000000000000000000000000000 #
b00000000000000000000000000000000 $
b00000000000000000000000000000000 %
0&
1'
b00000000 (
b00000000 )
0*
b00000000 +
1,
b00000000000000000000000000000000 -
b00000000000000000000000000001000 .
b00000000000000000000000000000100 /
#5
1&
#10
0&
0'
b00000001 (
b00001010 )
1*
0,
b00000000000000000000000000000100 -
#15
b00000000000000000000000000000001 #
b00000000000000000000000000001010 $
b00000000000000000000000000000100 %
1&
b00001010 +
1,
b00000000000000000000000000000000 -
#20
0&
0*
#25
1&
#30
0&
b00000010 (
b00000000 +
0,
b00000000000000000000000000000100 -
#35
1&
#40
0&
b00010100 )
1*
#45
b00000000000000000000000100000010 #
b00000000000000000000101000010100 $
1&
b00010100 +
1,
b00000000000000000000000000000000 -
#50
0&
0*
#55
1&
#60
0&
b00000001 (
b00001010 +
b00000000000000000000000000000001 -
#65
1&
#70
0&
b00000010 (
b00010100 +
b00000000000000000000000000000000 -
#75
1&
#80
0&
b00000011 (
b00000000 +
0,
b00000000000000000000000000000100 -
