notebooks/Chapter_6_examples/example_8__ring_counter/ring_counter_design.sv
// ring_counter_design.sv
module ring_counter_4bit (
    input  logic clock,
    input  logic reset_n,
    input  logic enable,
    output logic [3:0] ring_output
);

    // 4-bit ring counter register
    logic [3:0] ring_register;
    
    always_ff @(posedge clock or negedge reset_n) begin
        if (!reset_n) begin
            // Initialize with one bit set (start pattern)
            ring_register <= 4'b0001;
        end
        else if (enable) begin
            // Circular shift: MSB feeds back to LSB
            ring_register <= {ring_register[2:0], ring_register[3]};
        end
    end
    
    // Output the ring register state
    assign ring_output = ring_register;
    
    // Display current state for debugging
    always @(posedge clock) begin
        if (enable && reset_n) begin
            $display("Ring Counter: %b", ring_register);
        end
    end

endmodule

notebooks/Chapter_6_examples/example_8__ring_counter/ring_counter_design_testbench.sv
// ring_counter_design_testbench.sv
module ring_counter_testbench;
    
    // Testbench signals
    logic clock;
    logic reset_n;
    logic enable;
    logic [3:0] ring_output;
    
    // Instantiate the ring counter design
    ring_counter_4bit RING_COUNTER_INSTANCE (
        .clock(clock),
        .reset_n(reset_n),
        .enable(enable),
        .ring_output(ring_output)
    );
    
    // Clock generation (10ns period)
    initial begin
        clock = 0;
        forever #5 clock = ~clock;
    end
    
    // Test sequence
    initial begin
        // Setup waveform dumping
        $dumpfile("ring_counter_testbench.vcd");
        $dumpvars(0, ring_counter_testbench);
        
        // Display header
        $display();
        $display("=== 4-Bit Ring Counter Test ===");
        $display("Time | Reset | Enable | Output");
        $display("---------------------------------");
        
        // Initialize signals
        reset_n = 0;
        enable = 0;
        
        // Apply reset
        #10;
        reset_n = 1;
        $display(" %3t |   %b   |    %b   | %b", $time, reset_n, enable, ring_output);
        
        // Enable the ring counter and observe the circular shift
        #5;
        enable = 1;
        
        // Run for several clock cycles to see the ring pattern
        repeat(12) begin
            #10;
            $display(" %3t |   %b   |    %b   | %b", $time, reset_n, enable, ring_output);
        end
        
        // Test disable functionality
        $display();
        $display("Testing disable...");
        enable = 0;
        #20;
        $display(" %3t |   %b   |    %b   | %b (disabled)", $time, reset_n, enable, ring_output);
        
        // Re-enable
        enable = 1;
        #20;
        $display(" %3t |   %b   |    %b   | %b (re-enabled)", $time, reset_n, enable, ring_output);
        
        // Test reset during operation
        $display();
        $display("Testing reset during operation...");
        #10;
        reset_n = 0;
        #10;
        reset_n = 1;
        $display(" %3t |   %b   |    %b   | %b (after reset)", $time, reset_n, enable, ring_output);
        
        $display();
        $display("=== Ring Counter Test Complete ===");
        $display();
        
        #20;
        $finish;
    end

endmodule

notebooks/Chapter_6_examples/example_8__ring_counter/ring_counter_testbench.vcd
$version Generated by VerilatedVcd $end
$timescale 1ps $end
 $scope module $rootio $end
 $upscope $end
 $scope module ring_counter_testbench $end
  $var wire 1 # clock $end
  $var wire 1 $ reset_n $end
  $var wire 1 % enable $end
  $var wire 4 & ring_output [3:0] $end
  $scope module RING_COUNTER_INSTANCE $end
   $var wire 1 # clock $end
   $var wire 1 $ reset_n $end
   $var wire 1 % enable $end
   $var wire 4 & ring_output [3:0] $end
   $var wire 4 & ring_register [3:0] $end
  $upscope $end
 $upscope $end
$enddefinitions $end


#0
0#
0$
0%
b0000 &
#5
1#
b0001 &
#10
0#
1$
#15
1#
1%
b0010 &
#20
0#
#25
1#
b0100 &
#30
0#
#35
1#
b1000 &
#40
0#
#45
1#
b0001 &
#50
0#
#55
1#
b0010 &
#60
0#
#65
1#
b0100 &
#70
0#
#75
1#
b1000 &
#80
0#
#85
1#
b0001 &
#90
0#
#95
1#
b0010 &
#100
0#
#105
1#
b0100 &
#110
0#
#115
1#
b1000 &
#120
0#
#125
1#
b0001 &
#130
0#
#135
1#
0%
#140
0#
#145
1#
#150
0#
#155
1#
1%
b0010 &
#160
0#
#165
1#
b0100 &
#170
0#
#175
1#
b1000 &
#180
0#
#185
1#
0$
b0001 &
#190
0#
#195
1#
1$
b0010 &
#200
0#
#205
1#
b0100 &
#210
0#
#215
1#
b1000 &
