notebooks/Chapter_5_examples/example_14__clocked_processor_interface/clocked_processor_interface.sv
// clocked_processor_interface.sv
module clocked_processor_interface (
  input  logic       clk,
  input  logic       rst_n,
  input  logic [7:0] data_in,
  input  logic       valid_in,
  output logic [7:0] data_out,
  output logic       valid_out,
  output logic       ready
);

  // Simple processor that doubles the input data
  logic [7:0] internal_data;
  
  always_ff @(posedge clk or negedge rst_n) begin
    if (!rst_n) begin
      data_out  <= 8'h00;
      valid_out <= 1'b0;
      ready     <= 1'b1;
      internal_data <= 8'h00;
    end else begin
      if (valid_in && ready) begin
        internal_data <= data_in;
        data_out      <= data_in << 1;  // Double the input
        valid_out     <= 1'b1;
        ready         <= 1'b0;          // Not ready for next cycle
      end else begin
        valid_out <= 1'b0;
        ready     <= 1'b1;              // Ready for new data
      end
    end
  end

  initial $display("Clocked processor interface initialized");

endmodule

notebooks/Chapter_5_examples/example_14__clocked_processor_interface/clocked_processor_interface_testbench.sv
// clocked_processor_interface_testbench.sv
module clocked_processor_interface_testbench;
  
  // Clock and reset
  logic clk;
  logic rst_n;
  
  // Interface signals
  logic [7:0] data_in;
  logic       valid_in;
  logic [7:0] data_out;
  logic       valid_out;
  logic       ready;

  // Clock generation
  initial begin
    clk = 0;
    forever #5 clk = ~clk;  // 10ns period
  end

  // Clocking block for driving inputs (setup before clock edge)
  clocking driver_cb @(posedge clk);
    default input #1step output #2ns;  // Input skew 1 step, output skew 2ns
    output data_in;
    output valid_in;
    input  ready;
  endclocking

  // Clocking block for monitoring outputs (sample after clock edge)
  clocking monitor_cb @(posedge clk);
    default input #3ns;  // Sample 3ns after clock edge
    input data_out;
    input valid_out;
    input ready;
  endclocking

  // Instantiate design under test
  clocked_processor_interface dut(
    .clk(clk),
    .rst_n(rst_n),
    .data_in(data_in),
    .valid_in(valid_in),
    .data_out(data_out),
    .valid_out(valid_out),
    .ready(ready)
  );

  // Test sequence
  initial begin
    // Dump waves
    $dumpfile("clocked_processor_interface_testbench.vcd");
    $dumpvars(0, clocked_processor_interface_testbench);
    
    $display("Starting clocked processor interface test");
    
    // Initialize signals
    rst_n = 0;
    data_in = 8'h00;
    valid_in = 0;
    
    // Reset sequence
    repeat(3) @(posedge clk);
    rst_n = 1;
    $display("Reset released at time %0t", $time);
    
    // Wait for ready
    wait(ready);
    
    // Test case 1: Send data 0x05
    @(driver_cb);
    driver_cb.data_in <= 8'h05;
    driver_cb.valid_in <= 1'b1;
    $display("Sending data 0x05 at time %0t", $time);
    
    @(driver_cb);
    driver_cb.valid_in <= 1'b0;
    
    // Wait for output and check
    @(monitor_cb iff monitor_cb.valid_out);
    $display("Received data 0x%02h at time %0t (expected 0x0A)", monitor_cb.data_out, $time);
    
    // Test case 2: Send data 0x0F
    wait(monitor_cb.ready);
    @(driver_cb);
    driver_cb.data_in <= 8'h0F;
    driver_cb.valid_in <= 1'b1;
    $display("Sending data 0x0F at time %0t", $time);
    
    @(driver_cb);
    driver_cb.valid_in <= 1'b0;
    
    // Wait for output and check
    @(monitor_cb iff monitor_cb.valid_out);
    $display("Received data 0x%02h at time %0t (expected 0x1E)", monitor_cb.data_out, $time);
    
    // Test case 3: Send data 0x80 (test overflow)
    wait(monitor_cb.ready);
    @(driver_cb);
    driver_cb.data_in <= 8'h80;
    driver_cb.valid_in <= 1'b1;
    $display("Sending data 0x80 at time %0t", $time);
    
    @(driver_cb);
    driver_cb.valid_in <= 1'b0;
    
    // Wait for output and check
    @(monitor_cb iff monitor_cb.valid_out);
    $display("Received data 0x%02h at time %0t (expected 0x00 due to overflow)", monitor_cb.data_out, $time);
    
    // Wait a few more cycles
    repeat(5) @(posedge clk);
    
    $display("Clocked processor interface test completed at time %0t", $time);
    $finish;
  end

  // Timeout watchdog
  initial begin
    #1000ns;
    $display("ERROR: Test timeout!");
    $finish;
  end

endmodule

notebooks/Chapter_5_examples/example_14__clocked_processor_interface/clocked_processor_interface_testbench.vcd
$version Generated by VerilatedVcd $end
$timescale 1ps $end
 $scope module $rootio $end
 $upscope $end
 $scope module clocked_processor_interface_testbench $end
  $var wire 1 ' clk $end
  $var wire 1 ( rst_n $end
  $var wire 8 ) data_in [7:0] $end
  $var wire 1 * valid_in $end
  $var wire 8 # data_out [7:0] $end
  $var wire 1 $ valid_out $end
  $var wire 1 % ready $end
  $scope module dut $end
   $var wire 1 ' clk $end
   $var wire 1 ( rst_n $end
   $var wire 8 ) data_in [7:0] $end
   $var wire 1 * valid_in $end
   $var wire 8 # data_out [7:0] $end
   $var wire 1 $ valid_out $end
   $var wire 1 % ready $end
   $var wire 8 & internal_data [7:0] $end
  $upscope $end
 $upscope $end
$enddefinitions $end


#0
b00000000 #
0$
0%
b00000000 &
0'
0(
b00000000 )
0*
#5
1%
1'
#10
0'
#15
1'
#20
0'
#25
1'
1(
#30
0'
#35
1'
#40
0'
#45
1'
#50
0'
#55
1'
#60
0'
#65
1'
#70
0'
#75
1'
#80
0'
#85
1'
#90
0'
#95
1'
#100
0'
#105
1'
#110
0'
#115
1'
#120
0'
#125
1'
#130
0'
#135
1'
#140
0'
#145
1'
#150
0'
#155
1'
#160
0'
#165
1'
#170
0'
#175
1'
#180
0'
#185
1'
#190
0'
#195
1'
#200
0'
#205
1'
#210
0'
#215
1'
#220
0'
#225
1'
#230
0'
#235
1'
#240
0'
#245
1'
#250
0'
#255
1'
#260
0'
#265
1'
#270
0'
#275
1'
#280
0'
#285
1'
#290
0'
#295
1'
#300
0'
#305
1'
#310
0'
#315
1'
#320
0'
#325
1'
#330
0'
#335
1'
#340
0'
#345
1'
#350
0'
#355
1'
#360
0'
#365
1'
#370
0'
#375
1'
#380
0'
#385
1'
#390
0'
#395
1'
#400
0'
#405
1'
#410
0'
#415
1'
#420
0'
#425
1'
#430
0'
#435
1'
#440
0'
#445
1'
#450
0'
#455
1'
#460
0'
#465
1'
#470
0'
#475
1'
#480
0'
#485
1'
#490
0'
#495
1'
#500
0'
#505
1'
#510
0'
#515
1'
#520
0'
#525
1'
#530
0'
#535
1'
#540
0'
#545
1'
#550
0'
#555
1'
#560
0'
#565
1'
#570
0'
#575
1'
#580
0'
#585
1'
#590
0'
#595
1'
#600
0'
#605
1'
#610
0'
#615
1'
#620
0'
#625
1'
#630
0'
#635
1'
#640
0'
#645
1'
#650
0'
#655
1'
#660
0'
#665
1'
#670
0'
#675
1'
#680
0'
#685
1'
#690
0'
#695
1'
#700
0'
#705
1'
#710
0'
#715
1'
#720
0'
#725
1'
#730
0'
#735
1'
#740
0'
#745
1'
#750
0'
#755
1'
#760
0'
#765
1'
#770
0'
#775
1'
#780
0'
#785
1'
#790
0'
#795
1'
#800
0'
#805
1'
#810
0'
#815
1'
#820
0'
#825
1'
#830
0'
#835
1'
#840
0'
#845
1'
#850
0'
#855
1'
#860
0'
#865
1'
#870
0'
#875
1'
#880
0'
#885
1'
#890
0'
#895
1'
#900
0'
#905
1'
#910
0'
#915
1'
#920
0'
#925
1'
#930
0'
#935
1'
#940
0'
#945
1'
#950
0'
#955
1'
#960
0'
#965
1'
#970
0'
#975
1'
#980
0'
#985
1'
#990
0'
#995
1'
#1000
0'
#1005
1'
#1010
0'
#1015
1'
#1020
0'
#1025
1'
#1030
0'
#1035
1'
#1040
0'
#1045
1'
#1050
0'
#1055
1'
#1060
0'
#1065
1'
#1070
0'
#1075
1'
#1080
0'
#1085
1'
#1090
0'
#1095
1'
#1100
0'
#1105
1'
#1110
0'
#1115
1'
#1120
0'
#1125
1'
#1130
0'
#1135
1'
#1140
0'
#1145
1'
#1150
0'
#1155
1'
#1160
0'
#1165
1'
#1170
0'
#1175
1'
#1180
0'
#1185
1'
#1190
0'
#1195
1'
#1200
0'
#1205
1'
#1210
0'
#1215
1'
#1220
0'
#1225
1'
#1230
0'
#1235
1'
#1240
0'
#1245
1'
#1250
0'
#1255
1'
#1260
0'
#1265
1'
#1270
0'
#1275
1'
#1280
0'
#1285
1'
#1290
0'
#1295
1'
#1300
0'
#1305
1'
#1310
0'
#1315
1'
#1320
0'
#1325
1'
#1330
0'
#1335
1'
#1340
0'
#1345
1'
#1350
0'
#1355
1'
#1360
0'
#1365
1'
#1370
0'
#1375
1'
#1380
0'
#1385
1'
#1390
0'
#1395
1'
#1400
0'
#1405
1'
#1410
0'
#1415
1'
#1420
0'
#1425
1'
#1430
0'
#1435
1'
#1440
0'
#1445
1'
#1450
0'
#1455
1'
#1460
0'
#1465
1'
#1470
0'
#1475
1'
#1480
0'
#1485
1'
#1490
0'
#1495
1'
#1500
0'
#1505
1'
#1510
0'
#1515
1'
#1520
0'
#1525
1'
#1530
0'
#1535
1'
#1540
0'
#1545
1'
#1550
0'
#1555
1'
#1560
0'
#1565
1'
#1570
0'
#1575
1'
#1580
0'
#1585
1'
#1590
0'
#1595
1'
#1600
0'
#1605
1'
#1610
0'
#1615
1'
#1620
0'
#1625
1'
#1630
0'
#1635
1'
#1640
0'
#1645
1'
#1650
0'
#1655
1'
#1660
0'
#1665
1'
#1670
0'
#1675
1'
#1680
0'
#1685
1'
#1690
0'
#1695
1'
#1700
0'
#1705
1'
#1710
0'
#1715
1'
#1720
0'
#1725
1'
#1730
0'
#1735
1'
#1740
0'
#1745
1'
#1750
0'
#1755
1'
#1760
0'
#1765
1'
#1770
0'
#1775
1'
#1780
0'
#1785
1'
#1790
0'
#1795
1'
#1800
0'
#1805
1'
#1810
0'
#1815
1'
#1820
0'
#1825
1'
#1830
0'
#1835
1'
#1840
0'
#1845
1'
#1850
0'
#1855
1'
#1860
0'
#1865
1'
#1870
0'
#1875
1'
#1880
0'
#1885
1'
#1890
0'
#1895
1'
#1900
0'
#1905
1'
#1910
0'
#1915
1'
#1920
0'
#1925
1'
#1930
0'
#1935
1'
#1940
0'
#1945
1'
#1950
0'
#1955
1'
#1960
0'
#1965
1'
#1970
0'
#1975
1'
#1980
0'
#1985
1'
#1990
0'
#1995
1'
#2000
0'
#2005
1'
#2010
0'
#2015
1'
#2020
0'
#2025
1'
#2030
0'
#2035
b00001010 #
1$
0%
b00000101 &
1'
b00000101 )
1*
#2040
0'
#2045
0$
1%
1'
#2050
0'
#2055
1$
0%
1'
#2060
0'
#2065
0$
1%
1'
#2070
0'
#2075
1$
0%
1'
#2080
0'
#2085
0$
1%
1'
#2090
0'
#2095
1$
0%
1'
#2100
0'
#2105
0$
1%
1'
#2110
0'
#2115
1$
0%
1'
#2120
0'
#2125
0$
1%
1'
#2130
0'
#2135
1$
0%
1'
#2140
0'
#2145
0$
1%
1'
#2150
0'
#2155
1$
0%
1'
#2160
0'
#2165
0$
1%
1'
#2170
0'
#2175
1$
0%
1'
#2180
0'
#2185
0$
1%
1'
#2190
0'
#2195
1$
0%
1'
#2200
0'
#2205
0$
1%
1'
#2210
0'
#2215
1$
0%
1'
#2220
0'
#2225
0$
1%
1'
#2230
0'
#2235
1$
0%
1'
#2240
0'
#2245
0$
1%
1'
#2250
0'
#2255
1$
0%
1'
#2260
0'
#2265
0$
1%
1'
#2270
0'
#2275
1$
0%
1'
#2280
0'
#2285
0$
1%
1'
#2290
0'
#2295
1$
0%
1'
#2300
0'
#2305
0$
1%
1'
#2310
0'
#2315
1$
0%
1'
#2320
0'
#2325
0$
1%
1'
#2330
0'
#2335
1$
0%
1'
#2340
0'
#2345
0$
1%
1'
#2350
0'
#2355
1$
0%
1'
#2360
0'
#2365
0$
1%
1'
#2370
0'
#2375
1$
0%
1'
#2380
0'
#2385
0$
1%
1'
#2390
0'
#2395
1$
0%
1'
#2400
0'
#2405
0$
1%
1'
#2410
0'
#2415
1$
0%
1'
#2420
0'
#2425
0$
1%
1'
#2430
0'
#2435
1$
0%
1'
#2440
0'
#2445
0$
1%
1'
#2450
0'
#2455
1$
0%
1'
#2460
0'
#2465
0$
1%
1'
#2470
0'
#2475
1$
0%
1'
#2480
0'
#2485
0$
1%
1'
#2490
0'
#2495
1$
0%
1'
#2500
0'
#2505
0$
1%
1'
#2510
0'
#2515
1$
0%
1'
#2520
0'
#2525
0$
1%
1'
#2530
0'
#2535
1$
0%
1'
#2540
0'
#2545
0$
1%
1'
#2550
0'
#2555
1$
0%
1'
#2560
0'
#2565
0$
1%
1'
#2570
0'
#2575
1$
0%
1'
#2580
0'
#2585
0$
1%
1'
#2590
0'
#2595
1$
0%
1'
#2600
0'
#2605
0$
1%
1'
#2610
0'
#2615
1$
0%
1'
#2620
0'
#2625
0$
1%
1'
#2630
0'
#2635
1$
0%
1'
#2640
0'
#2645
0$
1%
1'
#2650
0'
#2655
1$
0%
1'
#2660
0'
#2665
0$
1%
1'
#2670
0'
#2675
1$
0%
1'
#2680
0'
#2685
0$
1%
1'
#2690
0'
#2695
1$
0%
1'
#2700
0'
#2705
0$
1%
1'
#2710
0'
#2715
1$
0%
1'
#2720
0'
#2725
0$
1%
1'
#2730
0'
#2735
1$
0%
1'
#2740
0'
#2745
0$
1%
1'
#2750
0'
#2755
1$
0%
1'
#2760
0'
#2765
0$
1%
1'
#2770
0'
#2775
1$
0%
1'
#2780
0'
#2785
0$
1%
1'
#2790
0'
#2795
1$
0%
1'
#2800
0'
#2805
0$
1%
1'
#2810
0'
#2815
1$
0%
1'
#2820
0'
#2825
0$
1%
1'
#2830
0'
#2835
1$
0%
1'
#2840
0'
#2845
0$
1%
1'
#2850
0'
#2855
1$
0%
1'
#2860
0'
#2865
0$
1%
1'
#2870
0'
#2875
1$
0%
1'
#2880
0'
#2885
0$
1%
1'
#2890
0'
#2895
1$
0%
1'
#2900
0'
#2905
0$
1%
1'
#2910
0'
#2915
1$
0%
1'
#2920
0'
#2925
0$
1%
1'
#2930
0'
#2935
1$
0%
1'
#2940
0'
#2945
0$
1%
1'
#2950
0'
#2955
1$
0%
1'
#2960
0'
#2965
0$
1%
1'
#2970
0'
#2975
1$
0%
1'
#2980
0'
#2985
0$
1%
1'
#2990
0'
#2995
1$
0%
1'
#3000
0'
#3005
0$
1%
1'
#3010
0'
#3015
1$
0%
1'
#3020
0'
#3025
0$
1%
1'
#3030
0'
#3035
1$
0%
1'
#3040
0'
#3045
0$
1%
1'
#3050
0'
#3055
1$
0%
1'
#3060
0'
#3065
0$
1%
1'
#3070
0'
#3075
1$
0%
1'
#3080
0'
#3085
0$
1%
1'
#3090
0'
#3095
1$
0%
1'
#3100
0'
#3105
0$
1%
1'
#3110
0'
#3115
1$
0%
1'
#3120
0'
#3125
0$
1%
1'
#3130
0'
#3135
1$
0%
1'
#3140
0'
#3145
0$
1%
1'
#3150
0'
#3155
1$
0%
1'
#3160
0'
#3165
0$
1%
1'
#3170
0'
#3175
1$
0%
1'
#3180
0'
#3185
0$
1%
1'
#3190
0'
#3195
1$
0%
1'
#3200
0'
#3205
0$
1%
1'
#3210
0'
#3215
1$
0%
1'
#3220
0'
#3225
0$
1%
1'
#3230
0'
#3235
1$
0%
1'
#3240
0'
#3245
0$
1%
1'
#3250
0'
#3255
1$
0%
1'
#3260
0'
#3265
0$
1%
1'
#3270
0'
#3275
1$
0%
1'
#3280
0'
#3285
0$
1%
1'
#3290
0'
#3295
1$
0%
1'
#3300
0'
#3305
0$
1%
1'
#3310
0'
#3315
1$
0%
1'
#3320
0'
#3325
0$
1%
1'
#3330
0'
#3335
1$
0%
1'
#3340
0'
#3345
0$
1%
1'
#3350
0'
#3355
1$
0%
1'
#3360
0'
#3365
0$
1%
1'
#3370
0'
#3375
1$
0%
1'
#3380
0'
#3385
0$
1%
1'
#3390
0'
#3395
1$
0%
1'
#3400
0'
#3405
0$
1%
1'
#3410
0'
#3415
1$
0%
1'
#3420
0'
#3425
0$
1%
1'
#3430
0'
#3435
1$
0%
1'
#3440
0'
#3445
0$
1%
1'
#3450
0'
#3455
1$
0%
1'
#3460
0'
#3465
0$
1%
1'
#3470
0'
#3475
1$
0%
1'
#3480
0'
#3485
0$
1%
1'
#3490
0'
#3495
1$
0%
1'
#3500
0'
#3505
0$
1%
1'
#3510
0'
#3515
1$
0%
1'
#3520
0'
#3525
0$
1%
1'
#3530
0'
#3535
1$
0%
1'
#3540
0'
#3545
0$
1%
1'
#3550
0'
#3555
1$
0%
1'
#3560
0'
#3565
0$
1%
1'
#3570
0'
#3575
1$
0%
1'
#3580
0'
#3585
0$
1%
1'
#3590
0'
#3595
1$
0%
1'
#3600
0'
#3605
0$
1%
1'
#3610
0'
#3615
1$
0%
1'
#3620
0'
#3625
0$
1%
1'
#3630
0'
#3635
1$
0%
1'
#3640
0'
#3645
0$
1%
1'
#3650
0'
#3655
1$
0%
1'
#3660
0'
#3665
0$
1%
1'
#3670
0'
#3675
1$
0%
1'
#3680
0'
#3685
0$
1%
1'
#3690
0'
#3695
1$
0%
1'
#3700
0'
#3705
0$
1%
1'
#3710
0'
#3715
1$
0%
1'
#3720
0'
#3725
0$
1%
1'
#3730
0'
#3735
1$
0%
1'
#3740
0'
#3745
0$
1%
1'
#3750
0'
#3755
1$
0%
1'
#3760
0'
#3765
0$
1%
1'
#3770
0'
#3775
1$
0%
1'
#3780
0'
#3785
0$
1%
1'
#3790
0'
#3795
1$
0%
1'
#3800
0'
#3805
0$
1%
1'
#3810
0'
#3815
1$
0%
1'
#3820
0'
#3825
0$
1%
1'
#3830
0'
#3835
1$
0%
1'
#3840
0'
#3845
0$
1%
1'
#3850
0'
#3855
1$
0%
1'
#3860
0'
#3865
0$
1%
1'
#3870
0'
#3875
1$
0%
1'
#3880
0'
#3885
0$
1%
1'
#3890
0'
#3895
1$
0%
1'
#3900
0'
#3905
0$
1%
1'
#3910
0'
#3915
1$
0%
1'
#3920
0'
#3925
0$
1%
1'
#3930
0'
#3935
1$
0%
1'
#3940
0'
#3945
0$
1%
1'
#3950
0'
#3955
1$
0%
1'
#3960
0'
#3965
0$
1%
1'
#3970
0'
#3975
1$
0%
1'
#3980
0'
#3985
0$
1%
1'
#3990
0'
#3995
1$
0%
1'
#4000
0'
#4005
0$
1%
1'
#4010
0'
#4015
1$
0%
1'
#4020
0'
#4025
0$
1%
1'
#4030
0'
#4035
1$
0%
1'
#4040
0'
#4045
0$
1%
1'
#4050
0'
#4055
1$
0%
1'
#4060
0'
#4065
0$
1%
1'
#4070
0'
#4075
1$
0%
1'
#4080
0'
#4085
0$
1%
1'
#4090
0'
#4095
1$
0%
1'
#4100
0'
#4105
0$
1%
1'
#4110
0'
#4115
1$
0%
1'
#4120
0'
#4125
0$
1%
1'
#4130
0'
#4135
1$
0%
1'
#4140
0'
#4145
0$
1%
1'
#4150
0'
#4155
1$
0%
1'
#4160
0'
#4165
0$
1%
1'
#4170
0'
#4175
1$
0%
1'
#4180
0'
#4185
0$
1%
1'
#4190
0'
#4195
1$
0%
1'
#4200
0'
#4205
0$
1%
1'
#4210
0'
#4215
1$
0%
1'
#4220
0'
#4225
0$
1%
1'
#4230
0'
#4235
1$
0%
1'
#4240
0'
#4245
0$
1%
1'
#4250
0'
#4255
1$
0%
1'
#4260
0'
#4265
0$
1%
1'
#4270
0'
#4275
1$
0%
1'
#4280
0'
#4285
0$
1%
1'
#4290
0'
#4295
1$
0%
1'
#4300
0'
#4305
0$
1%
1'
#4310
0'
#4315
1$
0%
1'
#4320
0'
#4325
0$
1%
1'
#4330
0'
#4335
1$
0%
1'
#4340
0'
#4345
0$
1%
1'
#4350
0'
#4355
1$
0%
1'
#4360
0'
#4365
0$
1%
1'
#4370
0'
#4375
1$
0%
1'
#4380
0'
#4385
0$
1%
1'
#4390
0'
#4395
1$
0%
1'
#4400
0'
#4405
0$
1%
1'
#4410
0'
#4415
1$
0%
1'
#4420
0'
#4425
0$
1%
1'
#4430
0'
#4435
1$
0%
1'
#4440
0'
#4445
0$
1%
1'
#4450
0'
#4455
1$
0%
1'
#4460
0'
#4465
0$
1%
1'
#4470
0'
#4475
1$
0%
1'
#4480
0'
#4485
0$
1%
1'
#4490
0'
#4495
1$
0%
1'
#4500
0'
#4505
0$
1%
1'
#4510
0'
#4515
1$
0%
1'
#4520
0'
#4525
0$
1%
1'
#4530
0'
#4535
1$
0%
1'
#4540
0'
#4545
0$
1%
1'
#4550
0'
#4555
1$
0%
1'
#4560
0'
#4565
0$
1%
1'
#4570
0'
#4575
1$
0%
1'
#4580
0'
#4585
0$
1%
1'
#4590
0'
#4595
1$
0%
1'
#4600
0'
#4605
0$
1%
1'
#4610
0'
#4615
1$
0%
1'
#4620
0'
#4625
0$
1%
1'
#4630
0'
#4635
1$
0%
1'
#4640
0'
#4645
0$
1%
1'
#4650
0'
#4655
1$
0%
1'
#4660
0'
#4665
0$
1%
1'
#4670
0'
#4675
1$
0%
1'
#4680
0'
#4685
0$
1%
1'
#4690
0'
#4695
1$
0%
1'
#4700
0'
#4705
0$
1%
1'
#4710
0'
#4715
1$
0%
1'
#4720
0'
#4725
0$
1%
1'
#4730
0'
#4735
1$
0%
1'
#4740
0'
#4745
0$
1%
1'
#4750
0'
#4755
1$
0%
1'
#4760
0'
#4765
0$
1%
1'
#4770
0'
#4775
1$
0%
1'
#4780
0'
#4785
0$
1%
1'
#4790
0'
#4795
1$
0%
1'
#4800
0'
#4805
0$
1%
1'
#4810
0'
#4815
1$
0%
1'
#4820
0'
#4825
0$
1%
1'
#4830
0'
#4835
1$
0%
1'
#4840
0'
#4845
0$
1%
1'
#4850
0'
#4855
1$
0%
1'
#4860
0'
#4865
0$
1%
1'
#4870
0'
#4875
1$
0%
1'
#4880
0'
#4885
0$
1%
1'
#4890
0'
#4895
1$
0%
1'
#4900
0'
#4905
0$
1%
1'
#4910
0'
#4915
1$
0%
1'
#4920
0'
#4925
0$
1%
1'
#4930
0'
#4935
1$
0%
1'
#4940
0'
#4945
0$
1%
1'
#4950
0'
#4955
1$
0%
1'
#4960
0'
#4965
0$
1%
1'
#4970
0'
#4975
1$
0%
1'
#4980
0'
#4985
0$
1%
1'
#4990
0'
#4995
1$
0%
1'
#5000
0'
#5005
0$
1%
1'
#5010
0'
#5015
1$
0%
1'
#5020
0'
#5025
0$
1%
1'
#5030
0'
#5035
1$
0%
1'
#5040
0'
#5045
0$
1%
1'
#5050
0'
#5055
1$
0%
1'
#5060
0'
#5065
0$
1%
1'
#5070
0'
#5075
1$
0%
1'
#5080
0'
#5085
0$
1%
1'
#5090
0'
#5095
1$
0%
1'
#5100
0'
#5105
0$
1%
1'
#5110
0'
#5115
1$
0%
1'
#5120
0'
#5125
0$
1%
1'
#5130
0'
#5135
1$
0%
1'
#5140
0'
#5145
0$
1%
1'
#5150
0'
#5155
1$
0%
1'
#5160
0'
#5165
0$
1%
1'
