notebooks/Chapter_6_examples/example_11__pwm_generator/pwm_generator_design.sv
// pwm_generator_design.sv
module pwm_generator_8bit (
    input  logic       clock,
    input  logic       reset_n,
    input  logic       enable,
    input  logic [7:0] duty_cycle,    // 0-255 (0% to 100% duty cycle)
    output logic       pwm_output,
    output logic [7:0] counter_value
);

    // 8-bit counter for PWM period
    logic [7:0] pwm_counter;
    
    // PWM counter logic
    always_ff @(posedge clock or negedge reset_n) begin
        if (!reset_n) begin
            pwm_counter <= 8'b0;
        end
        else if (enable) begin
            pwm_counter <= pwm_counter + 1;  // Auto-wraps at 255->0
        end
    end
    
    // PWM output generation
    // Output is HIGH when counter < duty_cycle, LOW otherwise
    assign pwm_output = enable ? (pwm_counter < duty_cycle) : 1'b0;
    
    // Counter output for monitoring
    assign counter_value = pwm_counter;
    
    // Display PWM parameters when duty cycle changes
    always @(duty_cycle) begin
        if (reset_n) begin
            real duty_percent;
            duty_percent = (duty_cycle * 100.0) / 256.0;
            $display("PWM Config: Duty Cycle = %d/256 (%.1f percent)", duty_cycle, duty_percent);
        end
    end
    
    // Optional: Display counter rollover
    always @(posedge clock) begin
        if (enable && reset_n && (pwm_counter == 8'hFF)) begin
            $display("PWM Period Complete (Counter rolled over)");
        end
    end

endmodule

notebooks/Chapter_6_examples/example_11__pwm_generator/pwm_generator_design_testbench.sv
// pwm_generator_design_testbench.sv
module pwm_generator_testbench;
    
    // Testbench signals
    logic       clock;
    logic       reset_n;
    logic       enable;
    logic [7:0] duty_cycle;
    logic       pwm_output;
    logic [7:0] counter_value;
    
    // Variables for duty cycle measurement
    integer high_count, total_count;
    real measured_duty;
    
    // Instantiate the PWM generator design
    pwm_generator_8bit PWM_GENERATOR_INSTANCE (
        .clock(clock),
        .reset_n(reset_n),
        .enable(enable),
        .duty_cycle(duty_cycle),
        .pwm_output(pwm_output),
        .counter_value(counter_value)
    );
    
    // Clock generation (10ns period = 100MHz)
    initial begin
        clock = 0;
        forever #5 clock = ~clock;
    end
    
    // Task to measure duty cycle over one complete period
    task measure_duty_cycle;
        input [7:0] expected_duty;
        begin
            high_count = 0;
            total_count = 0;
            
            // Wait for counter to start from 0
            while (counter_value != 0) @(posedge clock);
            
            // Measure for one complete period (256 clock cycles)
            repeat(256) begin
                @(posedge clock);
                if (pwm_output) high_count++;
                total_count++;
            end
            
            measured_duty = (high_count * 100.0) / total_count;
            $display("Expected: %d/256 (%.1f percent), Measured: %d/256 (%.1f percent) %s",
                     expected_duty, (expected_duty * 100.0)/256.0,
                     high_count, measured_duty,
                     (high_count == int'(expected_duty)) ? "✓" : "✗");
        end
    endtask
    
    // Test sequence
    initial begin
        // Setup waveform dumping
        $dumpfile("pwm_generator_testbench.vcd");
        $dumpvars(0, pwm_generator_testbench);
        
        // Display header
        $display();
        $display("=== 8-Bit PWM Generator Test ===");
        $display("PWM Frequency = Clock/256");
        $display("Resolution = 8 bits (256 steps)");
        $display();
        
        // Initialize signals
        reset_n = 0;
        enable = 0;
        duty_cycle = 0;
        
        // Apply reset
        #25;
        reset_n = 1;
        $display("=== RESET COMPLETE ===");
        #10;
        
        // Test 1: Different duty cycles
        $display();
        $display("=== TEST 1: Various Duty Cycles ===");
        
        enable = 1;
        
        // Test 0% duty cycle
        $display();
        $display("Testing 0 percent duty cycle:");
        duty_cycle = 8'd0;
        measure_duty_cycle(8'd0);
        
        // Test 25% duty cycle
        $display();
        $display("Testing 25 percent duty cycle:");
        duty_cycle = 8'd64;  // 64/256 = 25%
        measure_duty_cycle(8'd64);
        
        // Test 50% duty cycle
        $display();
        $display("Testing 50 percent duty cycle:");
        duty_cycle = 8'd128; // 128/256 = 50%
        measure_duty_cycle(8'd128);
        
        // Test 75% duty cycle
        $display();
        $display("Testing 75 percent duty cycle:");
        duty_cycle = 8'd192; // 192/256 = 75%
        measure_duty_cycle(8'd192);
        
        // Test 100% duty cycle
        $display();
        $display("Testing ~100 percent duty cycle:");
        duty_cycle = 8'd255; // 255/256 ≈ 99.6%
        measure_duty_cycle(8'd255);
        
        // Test 2: Dynamic duty cycle changes
        $display();
        $display("=== TEST 2: Dynamic Duty Cycle Changes ===");
        
        // Show real-time changes
        $display("Changing duty cycle every 0.5 periods...");
        
        duty_cycle = 8'd32;   // 12.5 percent
        #1280;  // 0.5 period (128 clocks)
        
        duty_cycle = 8'd96;   // 37.5 percent
        #1280;
        
        duty_cycle = 8'd160;  // 62.5 percent
        #1280;
        
        duty_cycle = 8'd224;  // 87.5 percent
        #1280;
        
        // Test 3: Enable/Disable functionality
        $display();
        $display("=== TEST 3: Enable/Disable Test ===");
        
        duty_cycle = 8'd128;  // 50 percent
        $display("PWM Enabled (50 percent duty cycle):");
        #500;
        
        enable = 0;
        $display("PWM Disabled (output should be 0):");
        #500;
        
        enable = 1;
        $display("PWM Re-enabled:");
        #500;
        
        // Test 4: Edge cases
        $display();
        $display("=== TEST 4: Edge Cases ===");
        
        // Minimum non-zero duty cycle
        $display();
        $display("Testing minimum duty cycle (1/256):");
        duty_cycle = 8'd1;
        measure_duty_cycle(8'd1);
        
        // Maximum duty cycle
        $display();
        $display("Testing maximum duty cycle (255/256):");
        duty_cycle = 8'd255;
        measure_duty_cycle(8'd255);
        
        // Show a few complete PWM periods with 50% duty cycle
        $display();
        $display("=== Showing 2 complete PWM periods (50 percent duty) ===");
        duty_cycle = 8'd128;
        
        repeat(512) begin  // 2 complete periods
            @(posedge clock);
            if (counter_value == 0) begin
                $display("--- New PWM Period Starting ---");
            end
        end
        
        $display();
        $display("=== PWM Generator Test Complete ===");
        $display();
        
        #100;
        $finish;
    end
    
    // Monitor PWM output transitions
    always @(pwm_output) begin
        if (reset_n && enable) begin
            $display("PWM: %s at counter=%d", pwm_output ? "HIGH" : "LOW", counter_value);
        end
    end

endmodule

notebooks/Chapter_6_examples/example_11__pwm_generator/pwm_generator_testbench.vcd
$version Generated by VerilatedVcd $end
$timescale 1ps $end
 $scope module $rootio $end
 $upscope $end
 $scope module pwm_generator_testbench $end
  $var wire 1 * clock $end
  $var wire 1 # reset_n $end
  $var wire 1 $ enable $end
  $var wire 8 % duty_cycle [7:0] $end
  $var wire 1 + pwm_output $end
  $var wire 8 , counter_value [7:0] $end
  $var wire 32 & high_count [31:0] $end
  $var wire 32 ' total_count [31:0] $end
  $var real 64 ( measured_duty $end
  $scope module PWM_GENERATOR_INSTANCE $end
   $var wire 1 * clock $end
   $var wire 1 # reset_n $end
   $var wire 1 $ enable $end
   $var wire 8 % duty_cycle [7:0] $end
   $var wire 1 + pwm_output $end
   $var wire 8 , counter_value [7:0] $end
   $var wire 8 , pwm_counter [7:0] $end
   $scope module unnamedblk1 $end
    $var real 64 - duty_percent $end
   $upscope $end
  $upscope $end
 $upscope $end
$enddefinitions $end


#0
0#
0$
b00000000 %
b00000000000000000000000000000000 &
b00000000000000000000000000000000 '
r0 (
0*
0+
b00000000 ,
r0 -
#5
1*
#10
0*
#15
1*
#20
0*
#25
1#
1*
#30
0*
#35
1$
1*
b00000001 ,
#40
0*
#45
b00000000000000000000000000000001 '
1*
b00000010 ,
#50
0*
#55
b00000000000000000000000000000010 '
1*
b00000011 ,
#60
0*
#65
b00000000000000000000000000000011 '
1*
b00000100 ,
#70
0*
#75
b00000000000000000000000000000100 '
1*
b00000101 ,
#80
0*
#85
b00000000000000000000000000000101 '
1*
b00000110 ,
#90
0*
#95
b00000000000000000000000000000110 '
1*
b00000111 ,
#100
0*
#105
b00000000000000000000000000000111 '
1*
b00001000 ,
#110
0*
#115
b00000000000000000000000000001000 '
1*
b00001001 ,
#120
0*
#125
b00000000000000000000000000001001 '
1*
b00001010 ,
#130
0*
#135
b00000000000000000000000000001010 '
1*
b00001011 ,
#140
0*
#145
b00000000000000000000000000001011 '
1*
b00001100 ,
#150
0*
#155
b00000000000000000000000000001100 '
1*
b00001101 ,
#160
0*
#165
b00000000000000000000000000001101 '
1*
b00001110 ,
#170
0*
#175
b00000000000000000000000000001110 '
1*
b00001111 ,
#180
0*
#185
b00000000000000000000000000001111 '
1*
b00010000 ,
#190
0*
#195
b00000000000000000000000000010000 '
1*
b00010001 ,
#200
0*
#205
b00000000000000000000000000010001 '
1*
b00010010 ,
#210
0*
#215
b00000000000000000000000000010010 '
1*
b00010011 ,
#220
0*
#225
b00000000000000000000000000010011 '
1*
b00010100 ,
#230
0*
#235
b00000000000000000000000000010100 '
1*
b00010101 ,
#240
0*
#245
b00000000000000000000000000010101 '
1*
b00010110 ,
#250
0*
#255
b00000000000000000000000000010110 '
1*
b00010111 ,
#260
0*
#265
b00000000000000000000000000010111 '
1*
b00011000 ,
#270
0*
#275
b00000000000000000000000000011000 '
1*
b00011001 ,
#280
0*
#285
b00000000000000000000000000011001 '
1*
b00011010 ,
#290
0*
#295
b00000000000000000000000000011010 '
1*
b00011011 ,
#300
0*
#305
b00000000000000000000000000011011 '
1*
b00011100 ,
#310
0*
#315
b00000000000000000000000000011100 '
1*
b00011101 ,
#320
0*
#325
b00000000000000000000000000011101 '
1*
b00011110 ,
#330
0*
#335
b00000000000000000000000000011110 '
1*
b00011111 ,
#340
0*
#345
b00000000000000000000000000011111 '
1*
b00100000 ,
#350
0*
#355
b00000000000000000000000000100000 '
1*
b00100001 ,
#360
0*
#365
b00000000000000000000000000100001 '
1*
b00100010 ,
#370
0*
#375
b00000000000000000000000000100010 '
1*
b00100011 ,
#380
0*
#385
b00000000000000000000000000100011 '
1*
b00100100 ,
#390
0*
#395
b00000000000000000000000000100100 '
1*
b00100101 ,
#400
0*
#405
b00000000000000000000000000100101 '
1*
b00100110 ,
#410
0*
#415
b00000000000000000000000000100110 '
1*
b00100111 ,
#420
0*
#425
b00000000000000000000000000100111 '
1*
b00101000 ,
#430
0*
#435
b00000000000000000000000000101000 '
1*
b00101001 ,
#440
0*
#445
b00000000000000000000000000101001 '
1*
b00101010 ,
#450
0*
#455
b00000000000000000000000000101010 '
1*
b00101011 ,
#460
0*
#465
b00000000000000000000000000101011 '
1*
b00101100 ,
#470
0*
#475
b00000000000000000000000000101100 '
1*
b00101101 ,
#480
0*
#485
b00000000000000000000000000101101 '
1*
b00101110 ,
#490
0*
#495
b00000000000000000000000000101110 '
1*
b00101111 ,
#500
0*
#505
b00000000000000000000000000101111 '
1*
b00110000 ,
#510
0*
#515
b00000000000000000000000000110000 '
1*
b00110001 ,
#520
0*
#525
b00000000000000000000000000110001 '
1*
b00110010 ,
#530
0*
#535
b00000000000000000000000000110010 '
1*
b00110011 ,
#540
0*
#545
b00000000000000000000000000110011 '
1*
b00110100 ,
#550
0*
#555
b00000000000000000000000000110100 '
1*
b00110101 ,
#560
0*
#565
b00000000000000000000000000110101 '
1*
b00110110 ,
#570
0*
#575
b00000000000000000000000000110110 '
1*
b00110111 ,
#580
0*
#585
b00000000000000000000000000110111 '
1*
b00111000 ,
#590
0*
#595
b00000000000000000000000000111000 '
1*
b00111001 ,
#600
0*
#605
b00000000000000000000000000111001 '
1*
b00111010 ,
#610
0*
#615
b00000000000000000000000000111010 '
1*
b00111011 ,
#620
0*
#625
b00000000000000000000000000111011 '
1*
b00111100 ,
#630
0*
#635
b00000000000000000000000000111100 '
1*
b00111101 ,
#640
0*
#645
b00000000000000000000000000111101 '
1*
b00111110 ,
#650
0*
#655
b00000000000000000000000000111110 '
1*
b00111111 ,
#660
0*
#665
b00000000000000000000000000111111 '
1*
b01000000 ,
#670
0*
#675
b00000000000000000000000001000000 '
1*
b01000001 ,
#680
0*
#685
b00000000000000000000000001000001 '
1*
b01000010 ,
#690
0*
#695
b00000000000000000000000001000010 '
1*
b01000011 ,
#700
0*
#705
b00000000000000000000000001000011 '
1*
b01000100 ,
#710
0*
#715
b00000000000000000000000001000100 '
1*
b01000101 ,
#720
0*
#725
b00000000000000000000000001000101 '
1*
b01000110 ,
#730
0*
#735
b00000000000000000000000001000110 '
1*
b01000111 ,
#740
0*
#745
b00000000000000000000000001000111 '
1*
b01001000 ,
#750
0*
#755
b00000000000000000000000001001000 '
1*
b01001001 ,
#760
0*
#765
b00000000000000000000000001001001 '
1*
b01001010 ,
#770
0*
#775
b00000000000000000000000001001010 '
1*
b01001011 ,
#780
0*
#785
b00000000000000000000000001001011 '
1*
b01001100 ,
#790
0*
#795
b00000000000000000000000001001100 '
1*
b01001101 ,
#800
0*
#805
b00000000000000000000000001001101 '
1*
b01001110 ,
#810
0*
#815
b00000000000000000000000001001110 '
1*
b01001111 ,
#820
0*
#825
b00000000000000000000000001001111 '
1*
b01010000 ,
#830
0*
#835
b00000000000000000000000001010000 '
1*
b01010001 ,
#840
0*
#845
b00000000000000000000000001010001 '
1*
b01010010 ,
#850
0*
#855
b00000000000000000000000001010010 '
1*
b01010011 ,
#860
0*
#865
b00000000000000000000000001010011 '
1*
b01010100 ,
#870
0*
#875
b00000000000000000000000001010100 '
1*
b01010101 ,
#880
0*
#885
b00000000000000000000000001010101 '
1*
b01010110 ,
#890
0*
#895
b00000000000000000000000001010110 '
1*
b01010111 ,
#900
0*
#905
b00000000000000000000000001010111 '
1*
b01011000 ,
#910
0*
#915
b00000000000000000000000001011000 '
1*
b01011001 ,
#920
0*
#925
b00000000000000000000000001011001 '
1*
b01011010 ,
#930
0*
#935
b00000000000000000000000001011010 '
1*
b01011011 ,
#940
0*
#945
b00000000000000000000000001011011 '
1*
b01011100 ,
#950
0*
#955
b00000000000000000000000001011100 '
1*
b01011101 ,
#960
0*
#965
b00000000000000000000000001011101 '
1*
b01011110 ,
#970
0*
#975
b00000000000000000000000001011110 '
1*
b01011111 ,
#980
0*
#985
b00000000000000000000000001011111 '
1*
b01100000 ,
#990
0*
#995
b00000000000000000000000001100000 '
1*
b01100001 ,
#1000
0*
#1005
b00000000000000000000000001100001 '
1*
b01100010 ,
#1010
0*
#1015
b00000000000000000000000001100010 '
1*
b01100011 ,
#1020
0*
#1025
b00000000000000000000000001100011 '
1*
b01100100 ,
#1030
0*
#1035
b00000000000000000000000001100100 '
1*
b01100101 ,
#1040
0*
#1045
b00000000000000000000000001100101 '
1*
b01100110 ,
#1050
0*
#1055
b00000000000000000000000001100110 '
1*
b01100111 ,
#1060
0*
#1065
b00000000000000000000000001100111 '
1*
b01101000 ,
#1070
0*
#1075
b00000000000000000000000001101000 '
1*
b01101001 ,
#1080
0*
#1085
b00000000000000000000000001101001 '
1*
b01101010 ,
#1090
0*
#1095
b00000000000000000000000001101010 '
1*
b01101011 ,
#1100
0*
#1105
b00000000000000000000000001101011 '
1*
b01101100 ,
#1110
0*
#1115
b00000000000000000000000001101100 '
1*
b01101101 ,
#1120
0*
#1125
b00000000000000000000000001101101 '
1*
b01101110 ,
#1130
0*
#1135
b00000000000000000000000001101110 '
1*
b01101111 ,
#1140
0*
#1145
b00000000000000000000000001101111 '
1*
b01110000 ,
#1150
0*
#1155
b00000000000000000000000001110000 '
1*
b01110001 ,
#1160
0*
#1165
b00000000000000000000000001110001 '
1*
b01110010 ,
#1170
0*
#1175
b00000000000000000000000001110010 '
1*
b01110011 ,
#1180
0*
#1185
b00000000000000000000000001110011 '
1*
b01110100 ,
#1190
0*
#1195
b00000000000000000000000001110100 '
1*
b01110101 ,
#1200
0*
#1205
b00000000000000000000000001110101 '
1*
b01110110 ,
#1210
0*
#1215
b00000000000000000000000001110110 '
1*
b01110111 ,
#1220
0*
#1225
b00000000000000000000000001110111 '
1*
b01111000 ,
#1230
0*
#1235
b00000000000000000000000001111000 '
1*
b01111001 ,
#1240
0*
#1245
b00000000000000000000000001111001 '
1*
b01111010 ,
#1250
0*
#1255
b00000000000000000000000001111010 '
1*
b01111011 ,
#1260
0*
#1265
b00000000000000000000000001111011 '
1*
b01111100 ,
#1270
0*
#1275
b00000000000000000000000001111100 '
1*
b01111101 ,
#1280
0*
#1285
b00000000000000000000000001111101 '
1*
b01111110 ,
#1290
0*
#1295
b00000000000000000000000001111110 '
1*
b01111111 ,
#1300
0*
#1305
b00000000000000000000000001111111 '
1*
b10000000 ,
#1310
0*
#1315
b00000000000000000000000010000000 '
1*
b10000001 ,
#1320
0*
#1325
b00000000000000000000000010000001 '
1*
b10000010 ,
#1330
0*
#1335
b00000000000000000000000010000010 '
1*
b10000011 ,
#1340
0*
#1345
b00000000000000000000000010000011 '
1*
b10000100 ,
#1350
0*
#1355
b00000000000000000000000010000100 '
1*
b10000101 ,
#1360
0*
#1365
b00000000000000000000000010000101 '
1*
b10000110 ,
#1370
0*
#1375
b00000000000000000000000010000110 '
1*
b10000111 ,
#1380
0*
#1385
b00000000000000000000000010000111 '
1*
b10001000 ,
#1390
0*
#1395
b00000000000000000000000010001000 '
1*
b10001001 ,
#1400
0*
#1405
b00000000000000000000000010001001 '
1*
b10001010 ,
#1410
0*
#1415
b00000000000000000000000010001010 '
1*
b10001011 ,
#1420
0*
#1425
b00000000000000000000000010001011 '
1*
b10001100 ,
#1430
0*
#1435
b00000000000000000000000010001100 '
1*
b10001101 ,
#1440
0*
#1445
b00000000000000000000000010001101 '
1*
b10001110 ,
#1450
0*
#1455
b00000000000000000000000010001110 '
1*
b10001111 ,
#1460
0*
#1465
b00000000000000000000000010001111 '
1*
b10010000 ,
#1470
0*
#1475
b00000000000000000000000010010000 '
1*
b10010001 ,
#1480
0*
#1485
b00000000000000000000000010010001 '
1*
b10010010 ,
#1490
0*
#1495
b00000000000000000000000010010010 '
1*
b10010011 ,
#1500
0*
#1505
b00000000000000000000000010010011 '
1*
b10010100 ,
#1510
0*
#1515
b00000000000000000000000010010100 '
1*
b10010101 ,
#1520
0*
#1525
b00000000000000000000000010010101 '
1*
b10010110 ,
#1530
0*
#1535
b00000000000000000000000010010110 '
1*
b10010111 ,
#1540
0*
#1545
b00000000000000000000000010010111 '
1*
b10011000 ,
#1550
0*
#1555
b00000000000000000000000010011000 '
1*
b10011001 ,
#1560
0*
#1565
b00000000000000000000000010011001 '
1*
b10011010 ,
#1570
0*
#1575
b00000000000000000000000010011010 '
1*
b10011011 ,
#1580
0*
#1585
b00000000000000000000000010011011 '
1*
b10011100 ,
#1590
0*
#1595
b00000000000000000000000010011100 '
1*
b10011101 ,
#1600
0*
#1605
b00000000000000000000000010011101 '
1*
b10011110 ,
#1610
0*
#1615
b00000000000000000000000010011110 '
1*
b10011111 ,
#1620
0*
#1625
b00000000000000000000000010011111 '
1*
b10100000 ,
#1630
0*
#1635
b00000000000000000000000010100000 '
1*
b10100001 ,
#1640
0*
#1645
b00000000000000000000000010100001 '
1*
b10100010 ,
#1650
0*
#1655
b00000000000000000000000010100010 '
1*
b10100011 ,
#1660
0*
#1665
b00000000000000000000000010100011 '
1*
b10100100 ,
#1670
0*
#1675
b00000000000000000000000010100100 '
1*
b10100101 ,
#1680
0*
#1685
b00000000000000000000000010100101 '
1*
b10100110 ,
#1690
0*
#1695
b00000000000000000000000010100110 '
1*
b10100111 ,
#1700
0*
#1705
b00000000000000000000000010100111 '
1*
b10101000 ,
#1710
0*
#1715
b00000000000000000000000010101000 '
1*
b10101001 ,
#1720
0*
#1725
b00000000000000000000000010101001 '
1*
b10101010 ,
#1730
0*
#1735
b00000000000000000000000010101010 '
1*
b10101011 ,
#1740
0*
#1745
b00000000000000000000000010101011 '
1*
b10101100 ,
#1750
0*
#1755
b00000000000000000000000010101100 '
1*
b10101101 ,
#1760
0*
#1765
b00000000000000000000000010101101 '
1*
b10101110 ,
#1770
0*
#1775
b00000000000000000000000010101110 '
1*
b10101111 ,
#1780
0*
#1785
b00000000000000000000000010101111 '
1*
b10110000 ,
#1790
0*
#1795
b00000000000000000000000010110000 '
1*
b10110001 ,
#1800
0*
#1805
b00000000000000000000000010110001 '
1*
b10110010 ,
#1810
0*
#1815
b00000000000000000000000010110010 '
1*
b10110011 ,
#1820
0*
#1825
b00000000000000000000000010110011 '
1*
b10110100 ,
#1830
0*
#1835
b00000000000000000000000010110100 '
1*
b10110101 ,
#1840
0*
#1845
b00000000000000000000000010110101 '
1*
b10110110 ,
#1850
0*
#1855
b00000000000000000000000010110110 '
1*
b10110111 ,
#1860
0*
#1865
b00000000000000000000000010110111 '
1*
b10111000 ,
#1870
0*
#1875
b00000000000000000000000010111000 '
1*
b10111001 ,
#1880
0*
#1885
b00000000000000000000000010111001 '
1*
b10111010 ,
#1890
0*
#1895
b00000000000000000000000010111010 '
1*
b10111011 ,
#1900
0*
#1905
b00000000000000000000000010111011 '
1*
b10111100 ,
#1910
0*
#1915
b00000000000000000000000010111100 '
1*
b10111101 ,
#1920
0*
#1925
b00000000000000000000000010111101 '
1*
b10111110 ,
#1930
0*
#1935
b00000000000000000000000010111110 '
1*
b10111111 ,
#1940
0*
#1945
b00000000000000000000000010111111 '
1*
b11000000 ,
#1950
0*
#1955
b00000000000000000000000011000000 '
1*
b11000001 ,
#1960
0*
#1965
b00000000000000000000000011000001 '
1*
b11000010 ,
#1970
0*
#1975
b00000000000000000000000011000010 '
1*
b11000011 ,
#1980
0*
#1985
b00000000000000000000000011000011 '
1*
b11000100 ,
#1990
0*
#1995
b00000000000000000000000011000100 '
1*
b11000101 ,
#2000
0*
#2005
b00000000000000000000000011000101 '
1*
b11000110 ,
#2010
0*
#2015
b00000000000000000000000011000110 '
1*
b11000111 ,
#2020
0*
#2025
b00000000000000000000000011000111 '
1*
b11001000 ,
#2030
0*
#2035
b00000000000000000000000011001000 '
1*
b11001001 ,
#2040
0*
#2045
b00000000000000000000000011001001 '
1*
b11001010 ,
#2050
0*
#2055
b00000000000000000000000011001010 '
1*
b11001011 ,
#2060
0*
#2065
b00000000000000000000000011001011 '
1*
b11001100 ,
#2070
0*
#2075
b00000000000000000000000011001100 '
1*
b11001101 ,
#2080
0*
#2085
b00000000000000000000000011001101 '
1*
b11001110 ,
#2090
0*
#2095
b00000000000000000000000011001110 '
1*
b11001111 ,
#2100
0*
#2105
b00000000000000000000000011001111 '
1*
b11010000 ,
#2110
0*
#2115
b00000000000000000000000011010000 '
1*
b11010001 ,
#2120
0*
#2125
b00000000000000000000000011010001 '
1*
b11010010 ,
#2130
0*
#2135
b00000000000000000000000011010010 '
1*
b11010011 ,
#2140
0*
#2145
b00000000000000000000000011010011 '
1*
b11010100 ,
#2150
0*
#2155
b00000000000000000000000011010100 '
1*
b11010101 ,
#2160
0*
#2165
b00000000000000000000000011010101 '
1*
b11010110 ,
#2170
0*
#2175
b00000000000000000000000011010110 '
1*
b11010111 ,
#2180
0*
#2185
b00000000000000000000000011010111 '
1*
b11011000 ,
#2190
0*
#2195
b00000000000000000000000011011000 '
1*
b11011001 ,
#2200
0*
#2205
b00000000000000000000000011011001 '
1*
b11011010 ,
#2210
0*
#2215
b00000000000000000000000011011010 '
1*
b11011011 ,
#2220
0*
#2225
b00000000000000000000000011011011 '
1*
b11011100 ,
#2230
0*
#2235
b00000000000000000000000011011100 '
1*
b11011101 ,
#2240
0*
#2245
b00000000000000000000000011011101 '
1*
b11011110 ,
#2250
0*
#2255
b00000000000000000000000011011110 '
1*
b11011111 ,
#2260
0*
#2265
b00000000000000000000000011011111 '
1*
b11100000 ,
#2270
0*
#2275
b00000000000000000000000011100000 '
1*
b11100001 ,
#2280
0*
#2285
b00000000000000000000000011100001 '
1*
b11100010 ,
#2290
0*
#2295
b00000000000000000000000011100010 '
1*
b11100011 ,
#2300
0*
#2305
b00000000000000000000000011100011 '
1*
b11100100 ,
#2310
0*
#2315
b00000000000000000000000011100100 '
1*
b11100101 ,
#2320
0*
#2325
b00000000000000000000000011100101 '
1*
b11100110 ,
#2330
0*
#2335
b00000000000000000000000011100110 '
1*
b11100111 ,
#2340
0*
#2345
b00000000000000000000000011100111 '
1*
b11101000 ,
#2350
0*
#2355
b00000000000000000000000011101000 '
1*
b11101001 ,
#2360
0*
#2365
b00000000000000000000000011101001 '
1*
b11101010 ,
#2370
0*
#2375
b00000000000000000000000011101010 '
1*
b11101011 ,
#2380
0*
#2385
b00000000000000000000000011101011 '
1*
b11101100 ,
#2390
0*
#2395
b00000000000000000000000011101100 '
1*
b11101101 ,
#2400
0*
#2405
b00000000000000000000000011101101 '
1*
b11101110 ,
#2410
0*
#2415
b00000000000000000000000011101110 '
1*
b11101111 ,
#2420
0*
#2425
b00000000000000000000000011101111 '
1*
b11110000 ,
#2430
0*
#2435
b00000000000000000000000011110000 '
1*
b11110001 ,
#2440
0*
#2445
b00000000000000000000000011110001 '
1*
b11110010 ,
#2450
0*
#2455
b00000000000000000000000011110010 '
1*
b11110011 ,
#2460
0*
#2465
b00000000000000000000000011110011 '
1*
b11110100 ,
#2470
0*
#2475
b00000000000000000000000011110100 '
1*
b11110101 ,
#2480
0*
#2485
b00000000000000000000000011110101 '
1*
b11110110 ,
#2490
0*
#2495
b00000000000000000000000011110110 '
1*
b11110111 ,
#2500
0*
#2505
b00000000000000000000000011110111 '
1*
b11111000 ,
#2510
0*
#2515
b00000000000000000000000011111000 '
1*
b11111001 ,
#2520
0*
#2525
b00000000000000000000000011111001 '
1*
b11111010 ,
#2530
0*
#2535
b00000000000000000000000011111010 '
1*
b11111011 ,
#2540
0*
#2545
b00000000000000000000000011111011 '
1*
b11111100 ,
#2550
0*
#2555
b00000000000000000000000011111100 '
1*
b11111101 ,
#2560
0*
#2565
b00000000000000000000000011111101 '
1*
b11111110 ,
#2570
0*
#2575
b00000000000000000000000011111110 '
1*
b11111111 ,
#2580
0*
#2585
b00000000000000000000000011111111 '
1*
b00000000 ,
#2590
0*
#2595
b01000000 %
b00000000000000000000000000000000 '
1*
1+
b00000001 ,
r25 -
#2600
0*
#2605
b00000000000000000000000000000001 &
b00000000000000000000000000000001 '
1*
b00000010 ,
#2610
0*
#2615
b00000000000000000000000000000010 &
b00000000000000000000000000000010 '
1*
b00000011 ,
#2620
0*
#2625
b00000000000000000000000000000011 &
b00000000000000000000000000000011 '
1*
b00000100 ,
#2630
0*
#2635
b00000000000000000000000000000100 &
b00000000000000000000000000000100 '
1*
b00000101 ,
#2640
0*
#2645
b00000000000000000000000000000101 &
b00000000000000000000000000000101 '
1*
b00000110 ,
#2650
0*
#2655
b00000000000000000000000000000110 &
b00000000000000000000000000000110 '
1*
b00000111 ,
#2660
0*
#2665
b00000000000000000000000000000111 &
b00000000000000000000000000000111 '
1*
b00001000 ,
#2670
0*
#2675
b00000000000000000000000000001000 &
b00000000000000000000000000001000 '
1*
b00001001 ,
#2680
0*
#2685
b00000000000000000000000000001001 &
b00000000000000000000000000001001 '
1*
b00001010 ,
#2690
0*
#2695
b00000000000000000000000000001010 &
b00000000000000000000000000001010 '
1*
b00001011 ,
#2700
0*
#2705
b00000000000000000000000000001011 &
b00000000000000000000000000001011 '
1*
b00001100 ,
#2710
0*
#2715
b00000000000000000000000000001100 &
b00000000000000000000000000001100 '
1*
b00001101 ,
#2720
0*
#2725
b00000000000000000000000000001101 &
b00000000000000000000000000001101 '
1*
b00001110 ,
#2730
0*
#2735
b00000000000000000000000000001110 &
b00000000000000000000000000001110 '
1*
b00001111 ,
#2740
0*
#2745
b00000000000000000000000000001111 &
b00000000000000000000000000001111 '
1*
b00010000 ,
#2750
0*
#2755
b00000000000000000000000000010000 &
b00000000000000000000000000010000 '
1*
b00010001 ,
#2760
0*
#2765
b00000000000000000000000000010001 &
b00000000000000000000000000010001 '
1*
b00010010 ,
#2770
0*
#2775
b00000000000000000000000000010010 &
b00000000000000000000000000010010 '
1*
b00010011 ,
#2780
0*
#2785
b00000000000000000000000000010011 &
b00000000000000000000000000010011 '
1*
b00010100 ,
#2790
0*
#2795
b00000000000000000000000000010100 &
b00000000000000000000000000010100 '
1*
b00010101 ,
#2800
0*
#2805
b00000000000000000000000000010101 &
b00000000000000000000000000010101 '
1*
b00010110 ,
#2810
0*
#2815
b00000000000000000000000000010110 &
b00000000000000000000000000010110 '
1*
b00010111 ,
#2820
0*
#2825
b00000000000000000000000000010111 &
b00000000000000000000000000010111 '
1*
b00011000 ,
#2830
0*
#2835
b00000000000000000000000000011000 &
b00000000000000000000000000011000 '
1*
b00011001 ,
#2840
0*
#2845
b00000000000000000000000000011001 &
b00000000000000000000000000011001 '
1*
b00011010 ,
#2850
0*
#2855
b00000000000000000000000000011010 &
b00000000000000000000000000011010 '
1*
b00011011 ,
#2860
0*
#2865
b00000000000000000000000000011011 &
b00000000000000000000000000011011 '
1*
b00011100 ,
#2870
0*
#2875
b00000000000000000000000000011100 &
b00000000000000000000000000011100 '
1*
b00011101 ,
#2880
0*
#2885
b00000000000000000000000000011101 &
b00000000000000000000000000011101 '
1*
b00011110 ,
#2890
0*
#2895
b00000000000000000000000000011110 &
b00000000000000000000000000011110 '
1*
b00011111 ,
#2900
0*
#2905
b00000000000000000000000000011111 &
b00000000000000000000000000011111 '
1*
b00100000 ,
#2910
0*
#2915
b00000000000000000000000000100000 &
b00000000000000000000000000100000 '
1*
b00100001 ,
#2920
0*
#2925
b00000000000000000000000000100001 &
b00000000000000000000000000100001 '
1*
b00100010 ,
#2930
0*
#2935
b00000000000000000000000000100010 &
b00000000000000000000000000100010 '
1*
b00100011 ,
#2940
0*
#2945
b00000000000000000000000000100011 &
b00000000000000000000000000100011 '
1*
b00100100 ,
#2950
0*
#2955
b00000000000000000000000000100100 &
b00000000000000000000000000100100 '
1*
b00100101 ,
#2960
0*
#2965
b00000000000000000000000000100101 &
b00000000000000000000000000100101 '
1*
b00100110 ,
#2970
0*
#2975
b00000000000000000000000000100110 &
b00000000000000000000000000100110 '
1*
b00100111 ,
#2980
0*
#2985
b00000000000000000000000000100111 &
b00000000000000000000000000100111 '
1*
b00101000 ,
#2990
0*
#2995
b00000000000000000000000000101000 &
b00000000000000000000000000101000 '
1*
b00101001 ,
#3000
0*
#3005
b00000000000000000000000000101001 &
b00000000000000000000000000101001 '
1*
b00101010 ,
#3010
0*
