notebooks/Chapter_6_examples/example_7__circular_shift_register/circular_shift_register.sv
// circular_shift_register.sv
// Simple 4-bit Circular Shift Register
// The MSB output feeds back to become the LSB input

module circular_shift_register (
    input  logic clk,         // Clock signal
    input  logic reset,       // Reset signal (active high)
    input  logic load,        // Load enable signal
    input  logic [3:0] data,  // 4-bit data to load
    output logic [3:0] q      // 4-bit register output
);

    // On each clock edge, shift left and feed MSB back to LSB
    always_ff @(posedge clk or posedge reset) begin
        if (reset) begin
            q <= 4'b0000;  // Clear register on reset
        end else if (load) begin
            q <= data;     // Load new data when load is asserted
        end else begin
            // Circular shift: MSB goes to LSB, others shift left
            q <= {q[2:0], q[3]};
        end
    end

    // Display the shifting pattern for simulation
    always @(posedge clk) begin
        if (!reset && !load) begin
            $display("Time %0t: Shift Register = %b", $time, q);
        end
    end

endmodule

notebooks/Chapter_6_examples/example_7__circular_shift_register/circular_shift_register_testbench.sv
// circular_shift_register_testbench.sv
// Simple testbench for circular shift register

module shift_register_testbench;

    // Test signals
    logic clk = 0;
    logic reset;
    logic load;
    logic [3:0] data;
    logic [3:0] q;

    // Clock generation - 10ns period
    always #5 clk = ~clk;

    // Instantiate the circular shift register
    circular_shift_register DUT (
        .clk(clk),
        .reset(reset),
        .load(load),
        .data(data),
        .q(q)
    );

    initial begin
        // Setup waveform dumping
        $dumpfile("shift_register_testbench.vcd");
        $dumpvars(0, shift_register_testbench);
        
        $display("=== Circular Shift Register Test ===");
        $display("Demonstrating 4-bit circular shift with feedback");
        $display();
        
        // Initialize signals
        reset = 1;
        load = 0;
        data = 4'b0000;
        
        // Wait a few clocks then release reset
        repeat(2) @(posedge clk);
        reset = 0;
        $display("Reset released");
        
        // Test 1: Load pattern 1001 and watch it shift
        $display("\nTest 1: Loading pattern 1001");
        @(posedge clk);
        load = 1;
        data = 4'b1001;
        @(posedge clk);
        load = 0;
        $display("Loaded: %b", q);
        
        // Watch it shift for 8 clock cycles (should return to original after 4)
        $display("\nShifting pattern (should repeat every 4 clocks):");
        for (int i = 0; i < 8; i++) begin
            @(posedge clk);
            $display("Clock %0d: %b", i+1, q);
        end
        
        // Test 2: Load different pattern 0110
        $display("\nTest 2: Loading pattern 0110");
        @(posedge clk);
        load = 1;
        data = 4'b0110;
        @(posedge clk);
        load = 0;
        $display("Loaded: %b", q);
        
        // Watch this pattern shift
        $display("\nShifting new pattern:");
        for (int i = 0; i < 6; i++) begin
            @(posedge clk);
            $display("Clock %0d: %b", i+1, q);
        end
        
        // Test 3: Single bit pattern to clearly show circular nature
        $display("\nTest 3: Single bit pattern 0001 (clearly shows circulation)");
        @(posedge clk);
        load = 1;
        data = 4'b0001;
        @(posedge clk);
        load = 0;
        $display("Loaded: %b", q);
        
        $display("\nWatching single bit circulate:");
        for (int i = 0; i < 8; i++) begin
            @(posedge clk);
            $display("Clock %0d: %b <- Bit position: %0d", i+1, q, 
                    (q == 4'b0010) ? 1 : 
                    (q == 4'b0100) ? 2 : 
                    (q == 4'b1000) ? 3 : 
                    (q == 4'b0001) ? 0 : -1);
        end
        
        $display("\n=== Test Complete ===");
        $display("Notice how the patterns repeat every 4 clock cycles");
        $display("This demonstrates the circular feedback from MSB to LSB");
        
        $finish;
    end

    // Monitor changes
    always @(q) begin
        if (!reset) begin
            $display("  Register changed to: %b (decimal: %0d)", q, q);
        end
    end

endmodule

notebooks/Chapter_6_examples/example_7__circular_shift_register/shift_register_testbench.vcd
$version Generated by VerilatedVcd $end
$timescale 1ps $end
 $scope module $rootio $end
 $upscope $end
 $scope module shift_register_testbench $end
  $var wire 1 ) clk $end
  $var wire 1 # reset $end
  $var wire 1 $ load $end
  $var wire 4 % data [3:0] $end
  $var wire 4 * q [3:0] $end
  $scope module DUT $end
   $var wire 1 ) clk $end
   $var wire 1 # reset $end
   $var wire 1 $ load $end
   $var wire 4 % data [3:0] $end
   $var wire 4 * q [3:0] $end
  $upscope $end
  $scope module unnamedblk1 $end
   $var wire 32 & i [31:0] $end
  $upscope $end
  $scope module unnamedblk2 $end
   $var wire 32 ' i [31:0] $end
  $upscope $end
  $scope module unnamedblk3 $end
   $var wire 32 ( i [31:0] $end
  $upscope $end
 $upscope $end
$enddefinitions $end


#0
1#
0$
b0000 %
b00000000000000000000000000000000 &
b00000000000000000000000000000000 '
b00000000000000000000000000000000 (
0)
b0000 *
#5
1)
#10
0)
#15
0#
1)
#20
0)
#25
1$
b1001 %
1)
b1001 *
#30
0)
#35
0$
1)
b0011 *
#40
0)
#45
b00000000000000000000000000000001 &
1)
b0110 *
#50
0)
#55
b00000000000000000000000000000010 &
1)
b1100 *
#60
0)
#65
b00000000000000000000000000000011 &
1)
b1001 *
#70
0)
#75
b00000000000000000000000000000100 &
1)
b0011 *
#80
0)
#85
b00000000000000000000000000000101 &
1)
b0110 *
#90
0)
#95
b00000000000000000000000000000110 &
1)
b1100 *
#100
0)
#105
b00000000000000000000000000000111 &
1)
b1001 *
#110
0)
#115
b00000000000000000000000000001000 &
1)
b0011 *
#120
0)
#125
1$
b0110 %
1)
b0110 *
#130
0)
#135
0$
1)
b1100 *
#140
0)
#145
b00000000000000000000000000000001 '
1)
b1001 *
#150
0)
#155
b00000000000000000000000000000010 '
1)
b0011 *
#160
0)
#165
b00000000000000000000000000000011 '
1)
b0110 *
#170
0)
#175
b00000000000000000000000000000100 '
1)
b1100 *
#180
0)
#185
b00000000000000000000000000000101 '
1)
b1001 *
#190
0)
#195
b00000000000000000000000000000110 '
1)
b0011 *
#200
0)
#205
1$
b0001 %
1)
b0001 *
#210
0)
#215
0$
1)
b0010 *
#220
0)
#225
b00000000000000000000000000000001 (
1)
b0100 *
#230
0)
#235
b00000000000000000000000000000010 (
1)
b1000 *
#240
0)
#245
b00000000000000000000000000000011 (
1)
b0001 *
#250
0)
#255
b00000000000000000000000000000100 (
1)
b0010 *
#260
0)
#265
b00000000000000000000000000000101 (
1)
b0100 *
#270
0)
#275
b00000000000000000000000000000110 (
1)
b1000 *
#280
0)
#285
b00000000000000000000000000000111 (
1)
b0001 *
#290
0)
#295
b00000000000000000000000000001000 (
1)
b0010 *
